Workbook
Name Anthropic: Paramètres!$P$2:$P$8
Name Google: Paramètres!$Q$3:$Q$6
Name MistralAI: Paramètres!$R$2:$R$8
Name Nb_requests: '⚙️Données'!$J$33:$L$33
Name Nb_tokens: '⚙️Données'!$J$36:$K$36
Name Nb_users: '⚙️Données'!$F$33:$H$33
Name OpenAI: Paramètres!$S$2:$S$16
Name Phase_conception: '⚙️Données'!$F$33:$L$33
Name Phase_production: '⚙️Données'!$J$36:$K$36
Name ZoneSaisie: '⚙️Données'!$F$26,'⚙️Données'!#REF!,'⚙️Données'!$J$26,'⚙️Données'!#REF!,'⚙️Données'!$L$26,'⚙️Données'!#REF!,'⚙️Données'!$K$36,'⚙️Données'!$L$33,'⚙️Données'!$H$33

Sheet 📓Notice
C2: Impact'IA
B6: Calculatrice des impacts environnementaux des projets mobilisant des modèles d'IA Générative
B8: Présentation du document
B9: Le développement et l’usage de modèles IA reposent sur des infrastructures techniques pouvant générer des impacts environnementaux significatifs. Cette calculatrice des impacts environnementaux des projets mobilisant des modèles d'IA Générative a été conçue par la Direction RSE et la Direction du Numérique Responsable du groupe SNCF, en collaboration avec Wavestone et Resilio. Objectif de la calculatrice Impact'IA : vous permettre, de manière autonome, d'évaluer trois dimensions environnementales clés associées à l'utilisation d'un modèle d'IA Générative dans votre projet, sur une année : la consommation électrique, le potentiel de réchauffement climatique (i.e. les émissions de gaz à effet de serre) ainsi que l'utilisation d'eau. Périmètre couvert : Impact'IA couvre une bibliothèque de 33 modèles d'IA Générative, correspondant aux principaux modèles des fournisseurs d'IA (Open AI, Anthropic, Mistral AI, Google)
B16: Précisions sur les 3 indicateurs environnementaux modélisés dans cette calculatrice :
B18: Consommation d'électricité | F18: Potentiel de Réchauffement Climatique | J18: Utilisation d'eau
B20: mWh ou Wh ou kWh | F20: mg CO₂e ou g CO₂e ou kg CO₂e | J20: mL ou L ou m³
B23: Guide Utilisateur
B24: Impact'IA est composé de 5 onglets visibles : 📓Notice (vous êtes ici) : Retrouvez la présentation de la calculatrice, ses objectifs, la méthodologie utilisée ainsi que les consignes d'utilisation. ⚙️Données : Renseignez la phase du projet, le modèle d'IA utilisé et les volumes d'usage. 📊Résultats : Visualisez les 3 impacts environnementaux de votre projet (par requête ou par an) ainsi que certaines équivalences. ♻️Bonnes pratiques : Explorez des leviers d'écoconception.
B33: Méthodologie de calcul
B70: Ce tutoriel explique comment ajouter un modèle supplémentaire dans la calculatrice Impact'IA, en respectant la structure du fichier Excel afin de garantir le bon fonctionnement des calculs et des filtres.
B72: Étapes 1. Afficher la feuille des modèles nommée "Modèles_IA" : Clic droit sur un onglet → Afficher… → Modèles_IA 2. Dupliquer une ligne existante : Dans l'onglet Modèles_IA, insérer ou copier / coller une ligne complète sur la ligne vide suivante (obligatoire pour conserver formules et listes déroulantes) 3. Renseigner les champs mentionnées : Nom du modèle, fournisseur, caractéristiques, sources, etc. 4. Vérifier : Dans l'onglet Données, le modèle apparaît dans les listes et les calculs se mettent à jour Bonne pratique : ne pas modifier les formules, colonnes ou cellules verrouillées.
B101: Des questions, difficultés ou suggestions d'améliorations ? | H101: https://github.com/SNCFdevelopers/ImpactIA
B105: Date | F105: Version | I105: Auteurs
B106: 46211 | F106: vF-CC-BY-NC-SA | I106: SNCF : Direction du Numérique Responsable en collaboration avec Wavestone et Resilio.
B107: 46281 | F107: vF-CC-BY-NC-SA | I107: Ajout du choix du mix électrique et de nouveaux modèles. Correction d'erreur dans le calcul du front applicatif. Mise à jour des FE électricité.
B109: Licence : CC-BY-NC-SA

Sheet ⚙️Données
C2: Impact'IA
B6: Calculatrice des impacts environnementaux des projets mobilisant des modèles d'IA Générative
B8: Comment utiliser cette calculatrice ?
B9: 1. Sélectionner la phase de votre projet : Conception ou Production 2. Choisir le fournisseur et le modèle d'IA 2. Renseigner le(s) volume(s) d'usage du projet (Pour les projets en Production, la valeur du nombre de tokens d'entrée et de sortie, ainsi que le nombre de requêtes par mois sont nécessaires. Si vous ne connaissez pas ces valeurs, sélectionnez la phase "Conception" et renseignez les valeurs demandées)
E19: Mon projet est en : | H19: Production
L25: {=IFERROR( FILTRER( Tableau1[Nom du modèle], Tableau1[Fournisseurs] = $F$26 ), "" )}
E26: Fournisseur : | I26: Modèle :
C33: Exemple de taille de requête | D33: Echange court (≈ 400 tokens) | F33: Nombre d'utilisateurs de l'outil: | H33: 1 | J33: Nombre de requêtes (par jour et par utilisateur) | L33: 1
C36: Nombre total de requêtes (par mois) | D36: 100000 | F36: Nombre total de tokens d'entrée (par mois) | H36: 100000000 | J36: Nombre total de tokens de sortie (par mois) | K36: 100000000
F38: Nombre de tokens d'embedding (par mois) | H38: 1000000000
B43: 2
D44: Je ne connais pas le pays d'inférence (valeur France par défaut) | G44: L'inférence a lieu en / au : (menu déroulant) | H44: France | J44: Je renseigne ma propre intensité carbone de l'électricité : | K44: 0 | L44: kgCO2e/kWh
H45: =TEXT(_xlfn.XLOOKUP('⚙️Données'!H44,Tableau2[Sous-catégorie],Tableau2[Valeur],"null"),"0,000")&" kgCO2e/kWh" -> 0,046 kgCO2e/kWh | L45: attention, valeur en kg

Sheet 📊Résultats
C2: Impact'IA
B6: Calculatrice des impacts environnementaux des projets mobilisant des modèles d'IA Générative
I23: Entraînement | L23: {="Inférence"&" : "&_xlfn.SWITCH('⚙️Données'!B43,2,"valeur France par défaut",1,'⚙️Données'!H44,3,"mix personalisé")} -> Inférence : valeur France par défaut
I24: =ROUND(Calcul!M84,2)&" kg CO₂e / kWh" -> 0,46 kg CO₂e / kWh | L24: =ROUND(Calcul!$M$210,2)&" kg CO₂e / kWh" -> 0,05 kg CO₂e / kWh
F41: Résultats > 1000 kgCO2e/an ➜ le projet doit faire l'objet d'une reflexion autour de son impact environnemental Résultats > 10 000 kgCO2e/an ➜ un plan d'action de mitigation des émissions et de mise en oeuvre de bonnes pratiques doit être mis en place.
E149: Les comparaisons de modèles sont réalisées à périmètre fonctionnel constant. Chaque modèle est rattaché à une catégorie de taille et d’usage, considérés comme des alternatives réalistes.
F157: GPT-4.1-mini | J157: Mistral Large | M157: Claude Sonnet 4 | Q157: Gemini 2.5 flash lite

Sheet ♻️Bonnes pratiques
D4: Impact'IA
B8: Calculatrice des impacts environnementaux des projets mobilisant des modèles d'IA Générative

Sheet Calcul
K2: Synthèse de comparaison
K3: Fournisseur | N3: =_xlfn.XLOOKUP(N4,Tableau1[Nom du modèle],Tableau1[Fournisseurs]) -> #N/A | O3: =_xlfn.XLOOKUP(O4,Tableau1[Nom du modèle],Tableau1[Fournisseurs]) -> OpenAI | P3: =_xlfn.XLOOKUP(P4,Tableau1[Nom du modèle],Tableau1[Fournisseurs]) -> Mistral AI | Q3: =_xlfn.XLOOKUP(Q4,Tableau1[Nom du modèle],Tableau1[Fournisseurs]) -> Anthropic | R3: =_xlfn.XLOOKUP(R4,Tableau1[Nom du modèle],Tableau1[Fournisseurs]) -> Google
K4: Modèles | N4: =N24 -> 0 | O4: =O24 -> GPT-4.1-mini | P4: =P24 -> Mistral Large | Q4: =Q24 -> Claude Sonnet 4 | R4: =R24 -> Gemini 2.5 flash lite
K6: =📓Notice!$B$18&" ("&L6&")" -> #DIV/0! | L6: =IF(N33>=1, " kWh / an", IF(N33>=0.001, " Wh / an", " mWh / an" ) ) -> #DIV/0! | N6: =IF($N$33>=1, TEXT(ROUND(N33,0),"# ##0"), IF($N$33>=0.001, TEXT(ROUND(N33*1000,2),"# ##0"), TEXT(ROUND(N33*1000000,0),"# ##0") ) )&" "&$L$6 -> #DIV/0! | O6: =IF($N$33>=1, TEXT(ROUND(O33,0),"# ##0"), IF($N$33>=0.001, TEXT(ROUND(O33*1000,2),"# ##0"), TEXT(ROUND(O33*1000000,0),"# ##0") ) )&" "&$L$6 -> #DIV/0! | P6: =IF($N$33>=1, TEXT(ROUND(P33,0),"# ##0"), IF($N$33>=0.001, TEXT(ROUND(P33*1000,2),"# ##0"), TEXT(ROUND(P33*1000000,0),"# ##0") ) )&" "&$L$6 -> #DIV/0! | Q6: =IF($N$33>=1, TEXT(ROUND(Q33,0),"# ##0"), IF($N$33>=0.001, TEXT(ROUND(Q33*1000,2),"# ##0"), TEXT(ROUND(Q33*1000000,0),"# ##0") ) )&" "&$L$6 -> #DIV/0! | R6: =IF($N$33>=1, TEXT(ROUND(R33,0),"# ##0"), IF($N$33>=0.001, TEXT(ROUND(R33*1000,2),"# ##0"), TEXT(ROUND(R33*1000000,0),"# ##0") ) )&" "&$L$6 -> #DIV/0!
K7: Ecart avec le modèle choisi | N7: =IF( N33/$N$33<1, "👍 x "&TEXT(N33/$N$33,"0,0"), "x "&TEXT(ROUNDUP(N33/$N$33,1),"0,0") ) -> #DIV/0! | O7: =IF( O33/$N$33<1, "👍 x "&TEXT(O33/$N$33,"0,0"), "x "&TEXT(ROUNDUP(O33/$N$33,1),"0,0") ) -> #DIV/0! | P7: =IF( P33/$N$33<1, "👍 x "&TEXT(P33/$N$33,"0,0"), "x "&TEXT(ROUNDUP(P33/$N$33,1),"0,0") ) -> #DIV/0! | Q7: =IF( Q33/$N$33<1, "👍 x "&TEXT(Q33/$N$33,"0,0"), "x "&TEXT(ROUNDUP(Q33/$N$33,1),"0,0") ) -> #DIV/0! | R7: =IF( R33/$N$33<1, "👍 x "&TEXT(R33/$N$33,"0,0"), "x "&TEXT(ROUNDUP(R33/$N$33,1),"0,0") ) -> #DIV/0!
K8: =📓Notice!$B$18&" par requête" -> Consommation d'électricité par requête | L8: =IF(N34>=1, " kWh / requête", IF(N34>=0.001, " Wh / requête", " mWh / requête" ) ) -> mWh / requête | N8: =IF($N$34>=1, ROUND(Calcul!N34,0), IF(Calcul!$N$34>=0.001, ROUND(Calcul!N34*1000,1), ROUND(Calcul!N34*1000000,0) ) )&" "&$L$8 -> 0 mWh / requête | O8: =IF($N$34>=1, ROUND(Calcul!O34,0), IF(Calcul!$N$34>=0.001, ROUND(Calcul!O34*1000,1), ROUND(Calcul!O34*1000000,0) ) )&" "&$L$8 -> 0 mWh / requête | P8: =IF($N$34>=1, ROUND(Calcul!P34,0), IF(Calcul!$N$34>=0.001, ROUND(Calcul!P34*1000,1), ROUND(Calcul!P34*1000000,0) ) )&" "&$L$8 -> 0 mWh / requête | Q8: =IF($N$34>=1, ROUND(Calcul!Q34,0), IF(Calcul!$N$34>=0.001, ROUND(Calcul!Q34*1000,1), ROUND(Calcul!Q34*1000000,0) ) )&" "&$L$8 -> 0 mWh / requête | R8: =IF($N$34>=1, ROUND(Calcul!R34,0), IF(Calcul!$N$34>=0.001, ROUND(Calcul!R34*1000,1), ROUND(Calcul!R34*1000000,0) ) )&" "&$L$8 -> 0 mWh / requête
K9: =📓Notice!$B$18&" par token de sortie" -> Consommation d'électricité par token de sortie | L9: =IF(Calcul!$N$35>=1000, " kWh / token", IF(N35>=0.001, " Wh / token", " mWh / token" ) ) -> mWh / token | N9: =IF(Calcul!$N$35>=1000, ROUND(Calcul!N35/1000,2), IF(Calcul!$N$35>=1, ROUND(Calcul!N35,2), ROUND(Calcul!N35*1000,2) ) )&" "&$L$9 -> 0 mWh / token | O9: =IF(Calcul!$N$35>=1000, ROUND(Calcul!O35/1000,2), IF(Calcul!$N$35>=1, ROUND(Calcul!O35,2), ROUND(Calcul!O35*1000,2) ) )&" "&$L$9 -> 0 mWh / token | P9: =IF(Calcul!$N$35>=1000, ROUND(Calcul!P35/1000,2), IF(Calcul!$N$35>=1, ROUND(Calcul!P35,2), ROUND(Calcul!P35*1000,2) ) )&" "&$L$9 -> 0 mWh / token | Q9: =IF(Calcul!$N$35>=1000, ROUND(Calcul!Q35/1000,2), IF(Calcul!$N$35>=1, ROUND(Calcul!Q35,2), ROUND(Calcul!Q35*1000,2) ) )&" "&$L$9 -> 0 mWh / token | R9: =IF(Calcul!$N$35>=1000, ROUND(Calcul!R35/1000,2), IF(Calcul!$N$35>=1, ROUND(Calcul!R35,2), ROUND(Calcul!R35*1000,2) ) )&" "&$L$9 -> 0 mWh / token
K11: =📓Notice!$F$18&" ("&L11&")" -> #DIV/0! | L11: =IF(N37>=1, " kg CO₂e / an", IF(N37>=0.001, " g CO₂e / an", " mg CO₂e / an" ) ) -> #DIV/0! | N11: =IF($N$37>=1, TEXT(ROUND(N37,0),"# ##0"), IF($N$37>=0.001, TEXT(ROUND(N37*1000,2),"# ##0"), TEXT(ROUND(N37*1000000,0),"# ##0") ) )&" "&$L$11 -> #DIV/0! | O11: =IF($N$37>=1, TEXT(ROUND(O37,0),"# ##0"), IF($N$37>=0.001, TEXT(ROUND(O37*1000,2),"# ##0"), TEXT(ROUND(O37*1000000,0),"# ##0") ) )&" "&$L$11 -> #DIV/0! | P11: =IF($N$37>=1, TEXT(ROUND(P37,0),"# ##0"), IF($N$37>=0.001, TEXT(ROUND(P37*1000,2),"# ##0"), TEXT(ROUND(P37*1000000,0),"# ##0") ) )&" "&$L$11 -> #DIV/0! | Q11: =IF($N$37>=1, TEXT(ROUND(Q37,0),"# ##0"), IF($N$37>=0.001, TEXT(ROUND(Q37*1000,2),"# ##0"), TEXT(ROUND(Q37*1000000,0),"# ##0") ) )&" "&$L$11 -> #DIV/0! | R11: =IF($N$37>=1, TEXT(ROUND(R37,0),"# ##0"), IF($N$37>=0.001, TEXT(ROUND(R37*1000,2),"# ##0"), TEXT(ROUND(R37*1000000,0),"# ##0") ) )&" "&$L$11 -> #DIV/0!
K12: Ecart avec le modèle choisi | N12: =IF( N37/$N$37<1, "👍 x "&TEXT(N37/$N$37,"0,0"), "x "&TEXT(ROUNDUP(N37/$N$37,1),"0,0") ) -> #DIV/0! | O12: =IF( O37/$N$37<1, "👍 x "&TEXT(O37/$N$37,"0,0"), "x "&TEXT(ROUNDUP(O37/$N$37,1),"0,0") ) -> #DIV/0! | P12: =IF( P37/$N$37<1, "👍 x "&TEXT(P37/$N$37,"0,0"), "x "&TEXT(ROUNDUP(P37/$N$37,1),"0,0") ) -> #DIV/0! | Q12: =IF( Q37/$N$37<1, "👍 x "&TEXT(Q37/$N$37,"0,0"), "x "&TEXT(ROUNDUP(Q37/$N$37,1),"0,0") ) -> #DIV/0! | R12: =IF( R37/$N$37<1, "👍 x "&TEXT(R37/$N$37,"0,0"), "x "&TEXT(ROUNDUP(R37/$N$37,1),"0,0") ) -> #DIV/0!
K13: =📓Notice!$F$18&" par requête" -> Potentiel de Réchauffement Climatique par requête | L13: =IF(N38>=1, " kg CO₂e / requête", IF(N38>=0.001, " g CO₂e / requête", " mg CO₂e / requête" ) ) -> mg CO₂e / requête | N13: =IF($N$38>=1, ROUND(N38,0), IF($N$38>=0.001, ROUND(N38*1000,1), ROUND(N38*1000000,0) ) )&" "&$L$13 -> 0 mg CO₂e / requête | O13: =IF($N$38>=1, ROUND(O38,0), IF($N$38>=0.001, ROUND(O38*1000,1), ROUND(O38*1000000,0) ) )&" "&$L$13 -> 0 mg CO₂e / requête | P13: =IF($N$38>=1, ROUND(P38,0), IF($N$38>=0.001, ROUND(P38*1000,1), ROUND(P38*1000000,0) ) )&" "&$L$13 -> 0 mg CO₂e / requête | Q13: =IF($N$38>=1, ROUND(Q38,0), IF($N$38>=0.001, ROUND(Q38*1000,1), ROUND(Q38*1000000,0) ) )&" "&$L$13 -> 0 mg CO₂e / requête | R13: =IF($N$38>=1, ROUND(R38,0), IF($N$38>=0.001, ROUND(R38*1000,1), ROUND(R38*1000000,0) ) )&" "&$L$13 -> 0 mg CO₂e / requête
K14: =📓Notice!$F$18&" par token de sortie" -> Potentiel de Réchauffement Climatique par token de sortie | L14: =IF($N$39>=1000, " kg CO₂e / token", IF($N$39>=0.001, " g CO₂e / token", " mg CO₂e / token" ) ) -> mg CO₂e / token | N14: =IF($N$39>=1000, ROUND(N39/1000,2), IF($N$39>=1, ROUND(N39,2), ROUND(N39*1000,2) ) )&" "&$L$14 -> 0 mg CO₂e / token | O14: =IF($N$39>=1000, ROUND(O39/1000,2), IF($N$39>=1, ROUND(O39,2), ROUND(O39*1000,2) ) )&" "&$L$14 -> 0 mg CO₂e / token | P14: =IF($N$39>=1000, ROUND(P39/1000,2), IF($N$39>=1, ROUND(P39,2), ROUND(P39*1000,2) ) )&" "&$L$14 -> 0 mg CO₂e / token | Q14: =IF($N$39>=1000, ROUND(Q39/1000,2), IF($N$39>=1, ROUND(Q39,2), ROUND(Q39*1000,2) ) )&" "&$L$14 -> 0 mg CO₂e / token | R14: =IF($N$39>=1000, ROUND(R39/1000,2), IF($N$39>=1, ROUND(R39,2), ROUND(R39*1000,2) ) )&" "&$L$14 -> 0 mg CO₂e / token
K16: =📓Notice!$J$18&" ("&L16&")" -> #DIV/0! | L16: =IF(N41>=1000, " m³ eq / an", IF(N41>=1, " L eq / an", " mL eq / an" ) ) -> #DIV/0! | N16: =ROUND(N$41/1000,0)&" "&$L$16 -> #DIV/0! | O16: =ROUND(O$41/1000,0)&" "&$L$16 -> #DIV/0! | P16: =ROUND(P$41/1000,0)&" "&$L$16 -> #DIV/0! | Q16: =ROUND(Q$41/1000,0)&" "&$L$16 -> #DIV/0! | R16: =ROUND(R$41/1000,0)&" "&$L$16 -> #DIV/0!
K17: Ecart avec le modèle choisi | N17: =IF( N41/$N$41<1, "👍 x "&TEXT(N41/$N$41,"0,0"), "x "&TEXT(ROUNDUP(N41/$N$41,1),"0,0") ) -> #DIV/0! | O17: =IF( O41/$N$41<1, "👍 x "&TEXT(O41/$N$41,"0,0"), "x "&TEXT(ROUNDUP(O41/$N$41,1),"0,0") ) -> #DIV/0! | P17: =IF( P41/$N$41<1, "👍 x "&TEXT(P41/$N$41,"0,0"), "x "&TEXT(ROUNDUP(P41/$N$41,1),"0,0") ) -> #DIV/0! | Q17: =IF( Q41/$N$41<1, "👍 x "&TEXT(Q41/$N$41,"0,0"), "x "&TEXT(ROUNDUP(Q41/$N$41,1),"0,0") ) -> #DIV/0! | R17: =IF( R41/$N$41<1, "👍 x "&TEXT(R41/$N$41,"0,0"), "x "&TEXT(ROUNDUP(R41/$N$41,1),"0,0") ) -> #DIV/0!
K18: =📓Notice!$J$18&" par requête" -> Utilisation d'eau par requête | L18: mL eq / requête | N18: =ROUND(N$42*1000,0)&" "&$L$18 -> 0 mL eq / requête | O18: =ROUND(O$42*1000,0)&" "&$L$18 -> 0 mL eq / requête | P18: =ROUND(P$42*1000,0)&" "&$L$18 -> 0 mL eq / requête | Q18: =ROUND(Q$42*1000,0)&" "&$L$18 -> 0 mL eq / requête | R18: =ROUND(R$42*1000,0)&" "&$L$18 -> 0 mL eq / requête
K19: =📓Notice!$J$18&" par token de sortie" -> Utilisation d'eau par token de sortie | L19: mL eq / token | N19: =ROUND(N$43*1000,2)&" "&$L$19 -> 0 mL eq / token | O19: =ROUND(O$43*1000,2)&" "&$L$19 -> 0 mL eq / token | P19: =ROUND(P$43*1000,2)&" "&$L$19 -> 0 mL eq / token | Q19: =ROUND(Q$43*1000,2)&" "&$L$19 -> 0 mL eq / token | R19: =ROUND(R$43*1000,2)&" "&$L$19 -> 0 mL eq / token
J21: Source de la formule | K21: Variable de calcul | L21: Unités | M21: Facteurs
K23: Caractéristique du modèle
C24: Sous étapes du cycle de vie | J24: Données | K24: Modèle sélectionné | L24: - | N24: ='⚙️Données'!$J$26 -> 0 | O24: =📊Résultats!$F$157 -> GPT-4.1-mini | P24: =📊Résultats!$J$157 -> Mistral Large | Q24: =📊Résultats!$M$157 -> Claude Sonnet 4 | R24: =📊Résultats!$Q$157 -> Gemini 2.5 flash lite
C25: ELEC | D25: Elec % | E25: GWP | F25: GES % | G25: WU | H25: EAU % | J25: Modèles_IA | K25: P_total | L25: Milliards de paramètres | N25: =IFERROR(INDEX(Tableau1[], MATCH(N$24, Tableau1[Nom du modèle], 0), MATCH($K$25, Tableau1[#Headers], 0)),0) -> 0 | O25: =IFERROR(INDEX(Tableau1[], MATCH(O$24, Tableau1[Nom du modèle], 0), MATCH($K$25, Tableau1[#Headers], 0)),0) -> 76 | P25: =IFERROR(INDEX(Tableau1[], MATCH(P$24, Tableau1[Nom du modèle], 0), MATCH($K$25, Tableau1[#Headers], 0)),0) -> 122 | Q25: =IFERROR(INDEX(Tableau1[], MATCH(Q$24, Tableau1[Nom du modèle], 0), MATCH($K$25, Tableau1[#Headers], 0)),0) -> 440 | R25: =IFERROR(INDEX(Tableau1[], MATCH(R$24, Tableau1[Nom du modèle], 0), MATCH($K$25, Tableau1[#Headers], 0)),0) -> 18
A26: Total | B26: Total | C26: =N33 -> #DIV/0! | D26: =C26/$C$26 -> #DIV/0! | E26: =N37 -> #DIV/0! | F26: =E26/$E$26 -> #DIV/0! | G26: =N41 -> #DIV/0! | H26: =G26/$G$26 -> #DIV/0! | J26: Modèles_IA | K26: P_active_moyenne | L26: Milliards de paramètres | N26: =IFERROR(INDEX(Tableau1[], MATCH(N$24, Tableau1[Nom du modèle], 0), MATCH($K$26, Tableau1[#Headers], 0)),0) -> 0 | O26: =IFERROR(INDEX(Tableau1[], MATCH(O$24, Tableau1[Nom du modèle], 0), MATCH($K$26, Tableau1[#Headers], 0)),0) -> 76 | P26: =IFERROR(INDEX(Tableau1[], MATCH(P$24, Tableau1[Nom du modèle], 0), MATCH($K$26, Tableau1[#Headers], 0)),0) -> 122 | Q26: =IFERROR(INDEX(Tableau1[], MATCH(Q$24, Tableau1[Nom du modèle], 0), MATCH($K$26, Tableau1[#Headers], 0)),0) -> 88 | R26: =IFERROR(INDEX(Tableau1[], MATCH(R$24, Tableau1[Nom du modèle], 0), MATCH($K$26, Tableau1[#Headers], 0)),0) -> 18
A27: Entrainement | B27: =J62 -> Stockage de la donnée d'entrainement | C27: =N64 -> #DIV/0! | D27: =C27/$C$26 -> #DIV/0! | E27: =N72 -> #DIV/0! | F27: =E27/$E$26 -> #DIV/0! | G27: =N76 -> #DIV/0! | H27: =G27/$G$26 -> #DIV/0! | J27: Données | K27: Nombre de tokens d'entrée générés par le projet | L27: tokens annuels | M27: =IF('⚙️Données'!$H$19="production",'⚙️Données'!$H$36*12,'⚙️Données'!$H$33*'⚙️Données'!$L$33*$M$30*365) -> 1200000000
B28: =J79 -> Expérimentations tests (R&D) | C28: =N81 -> #DIV/0! | D28: =C28/$C$26 -> #DIV/0! | E28: =N83 -> #DIV/0! | F28: =E28/$E$26 -> #DIV/0! | G28: =N86 -> #DIV/0! | H28: =G28/$G$26 -> #DIV/0! | J28: Données | K28: Nombre de tokens de sortie générés par le projet | L28: tokens annuels | M28: =IF('⚙️Données'!$H$19="production",'⚙️Données'!$K$36*12, '⚙️Données'!$H$33*'⚙️Données'!$L$33*IF('⚙️Données'!$D$33="",$M$31,_xlfn.XLOOKUP('⚙️Données'!$D$33,Paramètres!$B$2:$B$4,Paramètres!$C$2:$C$4)*365)) -> 1200000000
B29: =J88 -> Entrainement final du modèle | C29: =N90 -> #DIV/0! | D29: =C29/$C$26 -> #DIV/0! | E29: =N96 -> #DIV/0! | F29: =E29/$E$26 -> #DIV/0! | G29: =N99 -> #DIV/0! | H29: =G29/$G$26 -> #DIV/0! | J29: Modèles_IA | K29: Average TPS | M29: =IFERROR(INDEX(Tableau1[], MATCH(M$24, Tableau1[Nom du modèle], 0), MATCH($K$29, Tableau1[#Headers], 0)),0) -> 0 | N29: =IFERROR(INDEX(Tableau1[], MATCH(N$24, Tableau1[Nom du modèle], 0), MATCH($K$29, Tableau1[#Headers], 0)),0) -> 0 | O29: =IFERROR(INDEX(Tableau1[], MATCH(O$24, Tableau1[Nom du modèle], 0), MATCH($K$29, Tableau1[#Headers], 0)),0) -> 40.2 | P29: =IFERROR(INDEX(Tableau1[], MATCH(P$24, Tableau1[Nom du modèle], 0), MATCH($K$29, Tableau1[#Headers], 0)),0) -> 35.6 | Q29: =IFERROR(INDEX(Tableau1[], MATCH(Q$24, Tableau1[Nom du modèle], 0), MATCH($K$29, Tableau1[#Headers], 0)),0) -> 50 | R29: =IFERROR(INDEX(Tableau1[], MATCH(R$24, Tableau1[Nom du modèle], 0), MATCH($K$29, Tableau1[#Headers], 0)),0) -> 71.5
A30: Inférence | B30: =J122 -> RAG / Embedding (hors Conception) | C30: =N129 -> 0 | D30: =C30/$C$26 -> #DIV/0! | E30: =N136 -> 2.5395557 | F30: =E30/$E$26 -> #DIV/0! | G30: =N140 -> 859.96864 | H30: =G30/$G$26 -> #DIV/0! | J30: Bibliothèque_FE | K30: Moyenne de token d'entrée par requête | L30: tokens d'entrée par requête | M30: =IF('⚙️Données'!$H$19="Production",_xlfn.XLOOKUP($K$30,Tableau2[Variable],Tableau2[Valeur]),_xlfn.XLOOKUP('⚙️Données'!$D$33,Paramètres!$B$2:$B$4,Paramètres!$C$2:$C$4)*5) -> 5000
B31: =J144 -> Front applicatif - pré & post traitements | C31: =N146 -> 192.60426 | D31: =C31/$C$26 -> #DIV/0! | E31: =N151 -> 20.730337 | F31: =E31/$E$26 -> #DIV/0! | G31: =N155 -> 3179.8963 | H31: =G31/$G$26 -> #DIV/0! | J31: Bibliothèque_FE | K31: Moyenne de token de sortie par requête | L31: tokens de sortie par requête | M31: =IF('⚙️Données'!$H$19="Production",_xlfn.XLOOKUP($K$31,Tableau2[Variable],Tableau2[Valeur]),_xlfn.XLOOKUP('⚙️Données'!$D$33,Paramètres!$B$2:$B$4,Paramètres!$C$2:$C$4)) -> 1000
B32: =J161 -> Traitement des requêtes par le modèle | C32: =N163 -> #DIV/0! | D32: =C32/$C$26 -> #DIV/0! | E32: =N205 -> #DIV/0! | F32: =E32/$E$26 -> #DIV/0! | G32: =N235 -> #DIV/0! | H32: =G32/$G$26 -> #DIV/0!
K33: ÉLECTRICITÉ consommée pour le projet | L33: kWh | N33: =N$53+N$104 -> #DIV/0! | O33: =O$53+O$104 -> #DIV/0! | P33: =P$53+P$104 -> #DIV/0! | Q33: =Q$53+Q$104 -> #DIV/0! | R33: =R$53+R$104 -> #DIV/0!
K34: ÉLECTRICITÉ consommée (usage + environnée) pour un requête | L34: kWh | N34: =IFERROR(IF('⚙️Données'!$H$19="production",(N$33/('⚙️Données'!$D$36*12)),N$33/('⚙️Données'!$H$33*'⚙️Données'!$L$33*365)),0) -> 0 | O34: =IFERROR(IF('⚙️Données'!$H$19="production",(O$33/('⚙️Données'!$D$36*12)),O$33/('⚙️Données'!$H$33*'⚙️Données'!$L$33*365)),0) -> 0 | P34: =IFERROR(IF('⚙️Données'!$H$19="production",(P$33/('⚙️Données'!$D$36*12)),P$33/('⚙️Données'!$H$33*'⚙️Données'!$L$33*365)),0) -> 0 | Q34: =IFERROR(IF('⚙️Données'!$H$19="production",(Q$33/('⚙️Données'!$D$36*12)),Q$33/('⚙️Données'!$H$33*'⚙️Données'!$L$33*365)),0) -> 0 | R34: =IFERROR(IF('⚙️Données'!$H$19="production",(R$33/('⚙️Données'!$D$36*12)),R$33/('⚙️Données'!$H$33*'⚙️Données'!$L$33*365)),0) -> 0
B35: Electricité consommée pour le traitement de la requête à l'inférence | E35: Equivalents : | F35: Unité | G35: Eléments de base | H35: Affichage Résultats | K35: ÉLECTRICITÉ consommée (usage + environnée) pour un token | L35: kWh | N35: =IFERROR(N$33/$M$28,0) -> 0 | O35: =IFERROR(O$33/$M$28,0) -> 0 | P35: =IFERROR(P$33/$M$28,0) -> 0 | Q35: =IFERROR(Q$33/$M$28,0) -> 0 | R35: =IFERROR(R$33/$M$28,0) -> 0
B36: GPU | C36: =ROUND(N173,2) -> 48.64 | E36: =ROUNDUP(N33*1000,0) -> #DIV/0! | F36: Wh | G36: 1
B37: Serveur (hors GPU) | C37: =ROUND(N193,2) -> #DIV/0! | E37: =ROUNDUP($E$36*$G$37,0) -> #DIV/0! | F37: recharge(s) de smartphone | G37: 0.1 | H37: =TEXT(E37,"# ##0")&" "&Calcul!F37 -> #DIV/0! | K37: GES émis (usage + embarqué) pour le projet | L37: kg CO₂e | N37: =N$56+N$107 -> #DIV/0! | O37: =O$56+O$107 -> #DIV/0! | P37: =P$56+P$107 -> #DIV/0! | Q37: =Q$56+Q$107 -> #DIV/0! | R37: =R$56+R$107 -> #DIV/0!
B38: Equipements réseaux du centre de données | C38: =ROUND(N197,2) -> #DIV/0! | E38: =ROUNDUP($E$36*$G$38,0) -> #DIV/0! | F38: minute(s) sur Internet | G38: 0.6 | H38: =TEXT(E38,"# ##0")&" "&Calcul!F38 -> #DIV/0! | K38: GES émis (usage + embarqué) pour une requête | L38: kg CO₂e | N38: =IFERROR(IF('⚙️Données'!$H$19="production",(N$37/('⚙️Données'!$D$36*12)),N$37/('⚙️Données'!$H$33*'⚙️Données'!$L$33*365)),0) -> 0 | O38: =IFERROR(IF('⚙️Données'!$H$19="production",(O$37/('⚙️Données'!$D$36*12)),O$37/('⚙️Données'!$H$33*'⚙️Données'!$L$33*365)),0) -> 0 | P38: =IFERROR(IF('⚙️Données'!$H$19="production",(P$37/('⚙️Données'!$D$36*12)),P$37/('⚙️Données'!$H$33*'⚙️Données'!$L$33*365)),0) -> 0 | Q38: =IFERROR(IF('⚙️Données'!$H$19="production",(Q$37/('⚙️Données'!$D$36*12)),Q$37/('⚙️Données'!$H$33*'⚙️Données'!$L$33*365)),0) -> 0 | R38: =IFERROR(IF('⚙️Données'!$H$19="production",(R$37/('⚙️Données'!$D$36*12)),R$37/('⚙️Données'!$H$33*'⚙️Données'!$L$33*365)),0) -> 0
B39: Infrastructures techniques (inc. PUE) | C39: =N163-SUM(C36:C38) -> #DIV/0! | K39: GES émis (usage + embarqué) pour un token | L39: kg CO₂e | N39: =IFERROR(N$37/$M$28,0) -> 0 | O39: =IFERROR(O$37/$M$28,0) -> 0 | P39: =IFERROR(P$37/$M$28,0) -> 0 | Q39: =IFERROR(Q$37/$M$28,0) -> 0 | R39: =IFERROR(R$37/$M$28,0) -> 0
B40: Totale | C40: =SUM(C36:C39) -> #DIV/0! | E40: Equivalents | F40: Unité | G40: Eléments de base | H40: Affichage Résultats
E41: =N37*1000 -> #DIV/0! | F41: gCO2eq | G41: 1 | K41: EAU utilisée pour le projet | L41: L eq | N41: =N$59+N$110 -> #DIV/0! | O41: =O$59+O$110 -> #DIV/0! | P41: =P$59+P$110 -> #DIV/0! | Q41: =Q$59+Q$110 -> #DIV/0! | R41: =R$59+R$110 -> #DIV/0!
E42: =$E$41*G42 -> #DIV/0! | F42: km(s) en voiture | G42: 0.0046 | H42: =TEXT(E42,"# ##0")&" "&F42 -> #DIV/0! | K42: EAU utilisée pour une requête | L42: L eq | N42: =IFERROR(IF('⚙️Données'!$H$19="production",(N$41/('⚙️Données'!$D$36*12)),N$41/('⚙️Données'!$H$33*'⚙️Données'!$L$33*365)),0) -> 0 | O42: =IFERROR(IF('⚙️Données'!$H$19="production",(O$41/('⚙️Données'!$D$36*12)),O$41/('⚙️Données'!$H$33*'⚙️Données'!$L$33*365)),0) -> 0 | P42: =IFERROR(IF('⚙️Données'!$H$19="production",(P$41/('⚙️Données'!$D$36*12)),P$41/('⚙️Données'!$H$33*'⚙️Données'!$L$33*365)),0) -> 0 | Q42: =IFERROR(IF('⚙️Données'!$H$19="production",(Q$41/('⚙️Données'!$D$36*12)),Q$41/('⚙️Données'!$H$33*'⚙️Données'!$L$33*365)),0) -> 0 | R42: =IFERROR(IF('⚙️Données'!$H$19="production",(R$41/('⚙️Données'!$D$36*12)),R$41/('⚙️Données'!$H$33*'⚙️Données'!$L$33*365)),0) -> 0
E43: =$E$41*G43 -> #DIV/0! | F43: heure(s) de visio sur Teams | G43: =17.5/1000 -> 0.0175 | H43: =TEXT(E43,"# ##0")&" "&F43 -> #DIV/0! | K43: EAU utilisée pour un token | L43: L eq | N43: =IFERROR(N$41/$M$28,0) -> 0 | O43: =IFERROR(O$41/$M$28,0) -> 0 | P43: =IFERROR(P$41/$M$28,0) -> 0 | Q43: =IFERROR(Q$41/$M$28,0) -> 0 | R43: =IFERROR(R$41/$M$28,0) -> 0
E45: Equivalents | F45: Unité | G45: Eléments de base | H45: Affichage Résultats
E46: =N41 -> #DIV/0! | F46: L | G46: 1
E47: =$E$46*G47 -> #DIV/0! | F47: bouteille(s) d'eau | G47: 1 | H47: =TEXT(E47,"# ##0")&" "&F47 -> #DIV/0!
E48: =$E$46*G48 -> #DIV/0! | F48: café(s) bus | G48: 4 | H48: =TEXT(E48,"# ##0")&" "&F48 -> #DIV/0!
J51: Entrainement
K53: ÉLECTRICITÉ consommée pour l'entrainement, attribuable au projet | L53: kWh | N53: =N$64+N$81+N$90 -> #DIV/0! | O53: =O$64+O$81+O$90 -> #DIV/0! | P53: =P$64+P$81+P$90 -> #DIV/0! | Q53: =Q$64+Q$81+Q$90 -> #DIV/0! | R53: =R$64+R$81+R$90 -> #DIV/0!
K54: ÉLECTRICITÉ consommée de l'entrainement pour un token de sortie du projet | L54: kWh | N54: =IFERROR(N$53/$M$28,0) -> 0 | O54: =IFERROR(O$53/$M$28,0) -> 0 | P54: =IFERROR(P$53/$M$28,0) -> 0 | Q54: =IFERROR(Q$53/$M$28,0) -> 0 | R54: =IFERROR(R$53/$M$28,0) -> 0
K56: GES émis (usage + embarqué) de l'entrainement attribuable au projet | L56: kg CO₂e | N56: =N$72+N$83+N$96 -> #DIV/0! | O56: =O$72+O$83+O$96 -> #DIV/0! | P56: =P$72+P$83+P$96 -> #DIV/0! | Q56: =Q$72+Q$83+Q$96 -> #DIV/0! | R56: =R$72+R$83+R$96 -> #DIV/0!
K57: GES émis de l'entrainement pour un token de sortie du projet | L57: kg CO₂e | N57: =IFERROR(N$56/$M$28,0) -> 0 | O57: =IFERROR(O$56/$M$28,0) -> 0 | P57: =IFERROR(P$56/$M$28,0) -> 0 | Q57: =IFERROR(Q$56/$M$28,0) -> 0 | R57: =IFERROR(R$56/$M$28,0) -> 0
K59: EAU utilisée de l'entrainement attribuable au projet | L59: L eq | N59: =N$76+N$86+N$99 -> #DIV/0! | O59: =O$76+O$86+O$99 -> #DIV/0! | P59: =P$76+P$86+P$99 -> #DIV/0! | Q59: =Q$76+Q$86+Q$99 -> #DIV/0! | R59: =R$76+R$86+R$99 -> #DIV/0!
K60: EAU utilisée de l'entrainement pour un token de sortie du projet | L60: L eq | N60: =IFERROR(N$59/$M$28,0) -> 0 | O60: =IFERROR(O$59/$M$28,0) -> 0 | P60: =IFERROR(P$59/$M$28,0) -> 0 | Q60: =IFERROR(Q$59/$M$28,0) -> 0 | R60: =IFERROR(R$59/$M$28,0) -> 0
J62: Stockage de la donnée d'entrainement
J64: Enrichissement (hors périmètre Ecologits) | K64: ÉLECTRICITÉ consommée par le stockage de la donnée attribuable au projet | L64: kWh | N64: =N$68*($M$28/N$114) -> #DIV/0! | O64: =O$68*($M$28/O$114) -> #DIV/0! | P64: =P$68*($M$28/P$114) -> #DIV/0! | Q64: =Q$68*($M$28/Q$114) -> #DIV/0! | R64: =R$68*($M$28/R$114) -> #DIV/0!
J65: Enrichissement (hors périmètre Ecologits) | K65: Nombre de tokens à l'entrainement | L65: tokens | N65: =N$92/(6*(N$25*10^(9))) -> #DIV/0! | O65: =O$92/(6*(O$25*10^(9))) -> 3.444731e+12 | P65: =P$92/(6*(P$25*10^(9))) -> 1.5646226e+12 | Q65: =Q$92/(6*(Q$25*10^(9))) -> 1.619213e+12 | R65: =R$92/(6*(R$25*10^(9))) -> 7.6397416e+12
J66: Enrichissement (hors périmètre Ecologits) | K66: Volume de données stockées à l'entrainement | L66: To | N66: =ROUNDUP((N$65*(4*32)/8)/(1024^4),0) -> #DIV/0! | O66: =ROUNDUP((O$65*(4*32)/8)/(1024^4),0) -> 51 | P66: =ROUNDUP((P$65*(4*32)/8)/(1024^4),0) -> 23 | Q66: =ROUNDUP((Q$65*(4*32)/8)/(1024^4),0) -> 24 | R66: =ROUNDUP((R$65*(4*32)/8)/(1024^4),0) -> 112
J67: Enrichissement (hors périmètre Ecologits) | K67: Nombre de HDD 30To requis pour stocker la donnée | L67: HDD | N67: =ROUNDUP(N$66/30,0) -> #DIV/0! | O67: =ROUNDUP(O$66/30,0) -> 2 | P67: =ROUNDUP(P$66/30,0) -> 1 | Q67: =ROUNDUP(Q$66/30,0) -> 1 | R67: =ROUNDUP(R$66/30,0) -> 4
J68: Enrichissement (hors périmètre Ecologits) | K68: Consommation électrique du HDD pour le stockage dataset de l'entrainement | L68: kWh | N68: =Bibliothèque_FE!$D$10*N$67*N$165*$M$69*$M$70 -> #DIV/0! | O68: =Bibliothèque_FE!$D$10*O$67*O$165*$M$69*$M$70 -> 10.944 | P68: =Bibliothèque_FE!$D$10*P$67*P$165*$M$69*$M$70 -> 5.2896 | Q68: =Bibliothèque_FE!$D$10*Q$67*Q$165*$M$69*$M$70 -> 5.0844 | R68: =Bibliothèque_FE!$D$10*R$67*R$165*$M$69*$M$70 -> 19.8816
J69: Bibliothèque_FE | K69: Ratio d'usage HDD | L69: % | M69: =IFERROR(VLOOKUP($K$69,Tableau2[[Variable]:[Valeur]],2,FALSE()),0) -> 0.2
J70: Bibliothèque_FE | K70: Durée d'entrainement | L70: heures | M70: =IFERROR(_xlfn.XLOOKUP($K$70,Tableau2[Variable],Tableau2[Valeur]),0)*24 -> 2400
J72: Enrichissement (hors périmètre Ecologits) | K72: GES émis (usage + embarqué) du stockage de la donnée d'entrainement attribuable au projet | L72: kg CO₂e | N72: =(((($M$74/($M$73))*N$67*$M$70)/N$114)*$M$28)+(N$64*$M$84) -> #DIV/0! | O72: =(((($M$74/($M$73))*O$67*$M$70)/O$114)*$M$28)+(O$64*$M$84) -> #DIV/0! | P72: =(((($M$74/($M$73))*P$67*$M$70)/P$114)*$M$28)+(P$64*$M$84) -> #DIV/0! | Q72: =(((($M$74/($M$73))*Q$67*$M$70)/Q$114)*$M$28)+(Q$64*$M$84) -> #DIV/0! | R72: =(((($M$74/($M$73))*R$67*$M$70)/R$114)*$M$28)+(R$64*$M$84) -> #DIV/0!
J73: Bibliothèque_FE | K73: Durée de vie du HDD | L73: heures | M73: =(IFERROR(VLOOKUP($K$73,Tableau2[[Variable]:[Valeur]],2,FALSE()),0))*365*24 -> 43800
J74: Bibliothèque_FE | K74: GES embarqué du stockage HDD de l'entrainement | L74: kg CO₂e | M74: =(IFERROR(VLOOKUP($K$74,Tableau2[[Variable]:[Valeur]],2,FALSE()),0)) -> 640.5
J76: Enrichissement (hors périmètre Ecologits) | K76: EAU utilisée (usage + embarqué) par le stockage de la donnée attribuable au projet | L76: L eq | N76: =(N$64*N$237*$M$238)+(((($M$77/($M$73))*N$67*$M$70)/N$114)*$M$28) -> #DIV/0! | O76: =(O$64*O$237*$M$238)+(((($M$77/($M$73))*O$67*$M$70)/O$114)*$M$28) -> #DIV/0! | P76: =(P$64*P$237*$M$238)+(((($M$77/($M$73))*P$67*$M$70)/P$114)*$M$28) -> #DIV/0! | Q76: =(Q$64*Q$237*$M$238)+(((($M$77/($M$73))*Q$67*$M$70)/Q$114)*$M$28) -> #DIV/0! | R76: =(R$64*R$237*$M$238)+(((($M$77/($M$73))*R$67*$M$70)/R$114)*$M$28) -> #DIV/0!
J77: Bibliothèque_FE | K77: WU du stockage HDD de l'entrainement (WORLD) | L77: L eq | M77: =IFERROR(VLOOKUP($K77,Tableau2[[Variable]:[Valeur]],2,FALSE()),0) -> 163480
J79: Expérimentations tests (R&D)
J81: Enrichissement (hors périmètre Ecologits) | K81: ÉLECTRICITÉ consommée des expérimentations tests (R&D) attribuable au projet | L81: kWh | N81: =N$90*4 -> #DIV/0! | O81: =O$90*4 -> #DIV/0! | P81: =P$90*4 -> #DIV/0! | Q81: =Q$90*4 -> #DIV/0! | R81: =R$90*4 -> #DIV/0!
J83: Enrichissement (hors périmètre Ecologits) | K83: GES émis des expérimentations tests (R&D) pour le projet | L83: kg CO₂e | N83: =4*N$96 -> #DIV/0! | O83: =4*O$96 -> #DIV/0! | P83: =4*P$96 -> #DIV/0! | Q83: =4*Q$96 -> #DIV/0! | R83: =4*R$96 -> #DIV/0!
J84: Bibliothèque_FE | K84: Facteur d'émission de l'électricité consommée Monde | L84: kg CO₂e / kWh | M84: =IFERROR(VLOOKUP($K$84,Tableau2[[Variable]:[Valeur]],2,FALSE()),0) -> 0.458
J86: Enrichissement (hors périmètre Ecologits) | K86: EAU utilisée des expérimentations tests (R&D) pour le projet | L86: L eq | N86: =4*N$99 -> #DIV/0! | O86: =4*O$99 -> #DIV/0! | P86: =4*P$99 -> #DIV/0! | Q86: =4*Q$99 -> #DIV/0! | R86: =4*R$99 -> #DIV/0!
J88: Entrainement final du modèle
J90: Enrichissement (hors périmètre Ecologits) | K90: ÉLECTRICITÉ consommée pour l'entrainement final, attribuable au projet | L90: kWh | N90: =(((N$91)/N$114)*$M$28) -> #DIV/0! | O90: =((O$91)/O$114)*$M$28 -> #DIV/0! | P90: =((P$91)/P$114)*$M$28 -> #DIV/0! | Q90: =((Q$91)/Q$114)*$M$28 -> #DIV/0! | R90: =((R$91)/R$114)*$M$28 -> #DIV/0!
J91: Enrichissement (hors périmètre Ecologits) | K91: ÉLECTRICITÉ consommée au total pour l'entrainement | L91: kWh | N91: =((N$173+N$193+N$197)/N$173)*(((N$92*N$93)/3600)/1000)*N$165 -> #DIV/0! | O91: =((O$173+O$193+O$197)/O$173)*(((O$92*O$93)/3600)/1000)*O$165 -> 283900.36 | P91: =((P$173+P$193+P$197)/P$173)*(((P$92*P$93)/3600)/1000)*P$165 -> 195019.67 | Q91: =((Q$173+Q$193+Q$197)/Q$173)*(((Q$92*Q$93)/3600)/1000)*Q$165 -> 685206.65 | R91: =((R$173+R$193+R$197)/R$173)*(((R$92*R$93)/3600)/1000)*R$165 -> 133743.01
J92: Enrichissement (hors périmètre Ecologits) | K92: Nombre total de FLOPs requis pour l'entrainement | L92: FLOPS | N92: =10^(0.0006*N$94+17.151)*(N$25*10^9)^(0.541) -> 0 | O92: =10^(0.0006*O$94+17.151)*(O$25*10^9)^(0.541) -> 1.5707973e+24 | P92: =10^(0.0006*P$94+17.151)*(P$25*10^9)^(0.541) -> 1.1453037e+24 | Q92: =10^(0.0006*Q$94+17.151)*(Q$25*10^9)^(0.541) -> 4.2747222e+24 | R92: =10^(0.0006*R$94+17.151)*(R$25*10^9)^(0.541) -> 8.2509209e+23
J93: Enrichissement (hors périmètre Ecologits) | K93: Energie consommée pour un FLOP | L93: watt / FLOPS | N93: =1/IFERROR(INDEX(Tableau1[], MATCH(N$24, Tableau1[Nom du modèle], 0), MATCH($K$93, Tableau1[#Headers], 0)),0) -> #DIV/0! | O93: =1/IFERROR(INDEX(Tableau1[], MATCH(O$24, Tableau1[Nom du modèle], 0), MATCH($K$93, Tableau1[#Headers], 0)),0) -> 4.4444444e-13 | P93: =1/IFERROR(INDEX(Tableau1[], MATCH(P$24, Tableau1[Nom du modèle], 0), MATCH($K$93, Tableau1[#Headers], 0)),0) -> 4.4444444e-13 | Q93: =1/IFERROR(INDEX(Tableau1[], MATCH(Q$24, Tableau1[Nom du modèle], 0), MATCH($K$93, Tableau1[#Headers], 0)),0) -> 4.4444444e-13 | R93: =1/IFERROR(INDEX(Tableau1[], MATCH(R$24, Tableau1[Nom du modèle], 0), MATCH($K$93, Tableau1[#Headers], 0)),0) -> 4.4444444e-13
J94: Enrichissement (hors périmètre Ecologits) | K94: Nombre de jours entre janvier 2020 et la date de publication du modèle | L94: jours | N94: =IFERROR(INDEX(Tableau1[], MATCH(N$24, Tableau1[Nom du modèle], 0), MATCH("Date de publication", Tableau1[#Headers], 0)),0)-DATE(2020,1,1) -> -43831 | O94: =IFERROR(INDEX(Tableau1[], MATCH(O$24, Tableau1[Nom du modèle], 0), MATCH("Date de publication", Tableau1[#Headers], 0)),0)-DATE(2020,1,1) -> 1931 | P94: =IFERROR(INDEX(Tableau1[], MATCH(P$24, Tableau1[Nom du modèle], 0), MATCH("Date de publication", Tableau1[#Headers], 0)),0)-DATE(2020,1,1) -> 1517 | Q94: =IFERROR(INDEX(Tableau1[], MATCH(Q$24, Tableau1[Nom du modèle], 0), MATCH("Date de publication", Tableau1[#Headers], 0)),0)-DATE(2020,1,1) -> 1968 | R94: =IFERROR(INDEX(Tableau1[], MATCH(R$24, Tableau1[Nom du modèle], 0), MATCH("Date de publication", Tableau1[#Headers], 0)),0)-DATE(2020,1,1) -> 2029
J96: Enrichissement (hors périmètre Ecologits) | K96: GES émis (usage + embarqué) de l'entrainement final attribuable au projet | L96: kg CO₂e | N96: =(N$90*$M$84)+N$97 -> #DIV/0! | O96: =(O$90*$M$84)+O$97 -> #DIV/0! | P96: =(P$90*$M$84)+P$97 -> #DIV/0! | Q96: =(Q$90*$M$84)+Q$97 -> #DIV/0! | R96: =(R$90*$M$84)+R$97 -> #DIV/0!
J97: Enrichissement (hors périmètre Ecologits) | K97: GES embarqué de l'entrainement (ratio par rapport à l'inférence) | L97: kg CO₂e | N97: =(N$213/N$163)*N$90 -> #DIV/0! | O97: =(O$213/O$163)*O$90 -> #DIV/0! | P97: =(P$213/P$163)*P$90 -> #DIV/0! | Q97: =(Q$213/Q$163)*Q$90 -> #DIV/0! | R97: =(R$213/R$163)*R$90 -> #DIV/0!
J99: Enrichissement (hors périmètre Ecologits) | K99: EAU utilisée par l'entrainement final attribuable au projet | L99: L eq | N99: =(N$90*N$237*$M$238)+N$100 -> #DIV/0! | O99: =(O$90*O$237*$M$238)+O$100 -> #DIV/0! | P99: =(P$90*P$237*$M$238)+P$100 -> #DIV/0! | Q99: =(Q$90*Q$237*$M$238)+Q$100 -> #DIV/0! | R99: =(R$90*R$237*$M$238)+R$100 -> #DIV/0!
J100: Enrichissement (hors périmètre Ecologits) | K100: EAU embarquée par l'entrainement final (ratio par rapport à l'inférence) | L100: L eq | N100: =IFERROR((N235/N$163)*N$90,0) -> 0 | O100: =IFERROR((O235/O$163)*O$90,0) -> 0 | P100: =IFERROR((P235/P$163)*P$90,0) -> 0 | Q100: =IFERROR((Q235/Q$163)*Q$90,0) -> 0 | R100: =IFERROR((R235/R$163)*R$90,0) -> 0
J102: Inférence
K104: ÉLECTRICITÉ consommée de l'inférence pour le projet | L104: kWh | N104: =N$129+N$146+N$163 -> #DIV/0! | O104: =O$129+O$146+O$163 -> 269.17616 | P104: =P$129+P$146+P$163 -> 266.62377 | Q104: =Q$129+Q$146+Q$163 -> 263.75232 | R104: =R$129+R$146+R$163 -> 262.15707
K105: ÉLECTRICITÉ consommée (usage + environnée) de l'inférence pour un token | L105: kWh | N105: =IFERROR(N$104/$M$28,0) -> 0 | O105: =IFERROR(O$104/$M$28,0) -> 2.2431347e-07 | P105: =IFERROR(P$104/$M$28,0) -> 2.2218647e-07 | Q105: =IFERROR(Q$104/$M$28,0) -> 2.197936e-07 | R105: =IFERROR(R$104/$M$28,0) -> 2.1846423e-07
K107: GES émis (usage + embarqué) de l'inférence pour le projet | L107: kg CO₂e | N107: =N$136+N$151+N$205 -> #DIV/0! | O107: =O$136+O$151+O$205 -> 50.698098 | P107: =P$136+P$151+P$205 -> 54.377683 | Q107: =Q$136+Q$151+Q$205 -> 103.48394 | R107: =R$136+R$151+R$205 -> 30.713469
K108: GES émis (usage + embarqué) de l'inférence pour un token | L108: kg CO₂e | N108: =IFERROR(N$107/$M$28,0) -> 0 | O108: =IFERROR(O$107/$M$28,0) -> 4.2248415e-08 | P108: =IFERROR(P$107/$M$28,0) -> 4.5314736e-08 | Q108: =IFERROR(Q$107/$M$28,0) -> 8.6236621e-08 | R108: =IFERROR(R$107/$M$28,0) -> 2.5594558e-08
K110: EAU utilisée de l'inférence pour le projet | L110: L eq | N110: =N$140+N$155+N$235 -> #DIV/0! | O110: =O$140+O$155+O$235 -> 10590.846 | P110: =P$140+P$155+P$235 -> 11006.768 | Q110: =Q$140+Q$155+Q$235 -> 25410.962 | R110: =R$140+R$155+R$235 -> 5097.1349
K111: EAU utilisée de l'inférence pour un token | L111: L eq | N111: =IFERROR(N$110/$M$28,0) -> 0 | O111: =IFERROR(O$110/$M$28,0) -> 8.8257046e-06 | P111: =IFERROR(P$110/$M$28,0) -> 9.1723063e-06 | Q111: =IFERROR(Q$110/$M$28,0) -> 2.1175801e-05 | R111: =IFERROR(R$110/$M$28,0) -> 4.2476125e-06
J114: Enrichissement (hors périmètre Ecologits) | K114: Estimation du nombre de token du modele | L114: tokens générés sur la durée de vie du modèle | N114: =N$115*((365*24*3600)/(2*N$26*10^9))*N$120 -> #DIV/0! | O114: =O$115*((365*24*3600)/(2*O$26*10^9))*O$120 -> 0 | P114: =P$115*((365*24*3600)/(2*P$26*10^9))*P$120 -> 0 | Q114: =Q$115*((365*24*3600)/(2*Q$26*10^9))*Q$120 -> 0 | R114: =R$115*((365*24*3600)/(2*R$26*10^9))*R$120 -> 0
J115: Enrichissement (hors périmètre Ecologits) | K115: Nombre de FLOPS_model | L115: FLOPS | N115: =IFERROR(N$116*IFERROR(INDEX(Tableau1[], MATCH(N$24, Tableau1[Nom du modèle], 0), MATCH($K$93, Tableau1[#Headers], 0)),0)*(0.85*0.85),0) -> 0 | O115: =IFERROR(O$116*IFERROR(INDEX(Tableau1[], MATCH(O$24, Tableau1[Nom du modèle], 0), MATCH($K$93, Tableau1[#Headers], 0)),0)*(0.5*0.5*(1/O$165)*0.7),0) -> 0 | P115: =IFERROR(P$116*IFERROR(INDEX(Tableau1[], MATCH(P$24, Tableau1[Nom du modèle], 0), MATCH($K$93, Tableau1[#Headers], 0)),0)*(0.5*0.5*(1/P$165)*0.7),0) -> 0 | Q115: =IFERROR(Q$116*IFERROR(INDEX(Tableau1[], MATCH(Q$24, Tableau1[Nom du modèle], 0), MATCH($K$93, Tableau1[#Headers], 0)),0)*(0.5*0.5*(1/Q$165)*0.7),0) -> 0 | R115: =IFERROR(R$116*IFERROR(INDEX(Tableau1[], MATCH(R$24, Tableau1[Nom du modèle], 0), MATCH($K$93, Tableau1[#Headers], 0)),0)*(0.5*0.5*(1/R$165)*0.7),0) -> 0
J116: Enrichissement (hors périmètre Ecologits) | K116: Compute Model | L116: kW | N116: =(N$117*$M$118)/N$119 -> #DIV/0! | O116: =(O$117*$M$118)/O$119 -> #DIV/0! | P116: =(P$117*$M$118)/P$119 -> #DIV/0! | Q116: =(Q$117*$M$118)/Q$119 -> #DIV/0! | R116: =(R$117*$M$118)/R$119 -> #DIV/0!
J117: Modèles_IA | K117: Compute Capacity (kW) | L117: kW | N117: =IFERROR(INDEX(Tableau1[], MATCH(N$24, Tableau1[Nom du modèle], 0), MATCH($K$117, Tableau1[#Headers], 0)),0) -> 0 | O117: =IFERROR(INDEX(Tableau1[], MATCH(O$24, Tableau1[Nom du modèle], 0), MATCH($K$117, Tableau1[#Headers], 0)),0) -> 2000000 | P117: =IFERROR(INDEX(Tableau1[], MATCH(P$24, Tableau1[Nom du modèle], 0), MATCH($K$117, Tableau1[#Headers], 0)),0) -> 200000 | Q117: =IFERROR(INDEX(Tableau1[], MATCH(Q$24, Tableau1[Nom du modèle], 0), MATCH($K$117, Tableau1[#Headers], 0)),0) -> 1400000 | R117: =IFERROR(INDEX(Tableau1[], MATCH(R$24, Tableau1[Nom du modèle], 0), MATCH($K$117, Tableau1[#Headers], 0)),0) -> 9000000
J118: Bibliothèque_FE | K118: Ratio d'inférence sur la compute capacity | L118: % | M118: =IFERROR(_xlfn.XLOOKUP($K$118,Tableau2[Variable],Tableau2[Valeur]),0) -> 0.8
J119: Enrichissement (hors périmètre Ecologits) | K119: N_active_model | L119: modèles actifs | N119: =COUNTIFS(Tableau1[Date de publication],">="&EDATE(TODAY(),-24),Tableau1[Fournisseurs],'⚙️Données'!$F$26) -> 0 | O119: =COUNTIFS(Tableau1[Date de publication],">="&EDATE(TODAY(),-24),Tableau1[Fournisseurs],'⚙️Données'!$F$26) -> 0 | P119: =COUNTIFS(Tableau1[Date de publication],">="&EDATE(TODAY(),-24),Tableau1[Fournisseurs],'⚙️Données'!$F$26) -> 0 | Q119: =COUNTIFS(Tableau1[Date de publication],">="&EDATE(TODAY(),-24),Tableau1[Fournisseurs],'⚙️Données'!$F$26) -> 0 | R119: =COUNTIFS(Tableau1[Date de publication],">="&EDATE(TODAY(),-24),Tableau1[Fournisseurs],'⚙️Données'!$F$26) -> 0
J120: Enrichissement (hors périmètre Ecologits) | K120: Age du modèle | L120: année(s) | N120: 1.5 | O120: =IF( (TODAY() -_xlfn.XLOOKUP(O$24,Tableau1[Nom du modèle],Tableau1[Date de publication]))/365.25<=2, (TODAY()-_xlfn.XLOOKUP(O$24,Tableau1[Nom du modèle],Tableau1[Date de publication]))/365.25, 2) -> 1.4209446 | P120: =IF( (TODAY() -_xlfn.XLOOKUP(P$24,Tableau1[Nom du modèle],Tableau1[Date de publication]))/365.25<=2, (TODAY()-_xlfn.XLOOKUP(P$24,Tableau1[Nom du modèle],Tableau1[Date de publication]))/365.25, 2) -> 2 | Q120: =IF( (TODAY() -_xlfn.XLOOKUP(Q$24,Tableau1[Nom du modèle],Tableau1[Date de publication]))/365.25<=2, (TODAY()-_xlfn.XLOOKUP(Q$24,Tableau1[Nom du modèle],Tableau1[Date de publication]))/365.25, 2) -> 1.3196441 | R120: =IF( (TODAY() -_xlfn.XLOOKUP(R$24,Tableau1[Nom du modèle],Tableau1[Date de publication]))/365.25<=2, (TODAY()-_xlfn.XLOOKUP(R$24,Tableau1[Nom du modèle],Tableau1[Date de publication]))/365.25, 2) -> 1.1526352
J122: RAG / Embedding (hors Conception)
J124: Modèles_IA | K124: Modèle sélectionné | M124: text-embedding-3-large
J125: Modèles_IA | K125: P_total | L125: Milliards de paramètres | M125: =IFERROR(INDEX(Tableau1[], MATCH($M$124, Tableau1[Nom du modèle], 0), MATCH($K$125, Tableau1[#Headers], 0)),0) -> 8
J126: Enrichissement (hors périmètre Ecologits) | K126: Latence de génération pour l'embedding | L126: secondes | M126: =IF($M$127>0,((0.022*(($M$125*10^(9))/(8*10^(9)))*($M$127*$M$179)+97.394)/1000),0) -> 16896000
J127: Données | K127: #T_embedding | L127: tokens annuels | M127: =IF('⚙️Données'!$H$19="production",'⚙️Données'!$H$38*12, 0) -> 12000000000
J129: Enrichissement (hors périmètre Ecologits) | K129: ÉLECTRICITÉ consommée (usage + environné) pour l'embedding | L129: kWh | N129: =($M$132+$M$134)*N$165*1/$M$179 -> 0 | O129: =$M$130*($M$132+$M$134)*O$165*1/$M$179 -> 76.571902 | P129: =$M$130*($M$132+$M$134)*P$165*1/$M$179 -> 74.019506 | Q129: =$M$130*($M$132+$M$134)*Q$165*1/$M$179 -> 71.148059 | R129: =$M$130*($M$132+$M$134)*R$165*1/$M$179 -> 69.552811
J130: Bibliothèque_FE | K130: Nombre de GPU utilisé pour l'embedding | L130: unité(s) | M130: =(IFERROR(VLOOKUP($K$130,Tableau2[[Variable]:[Valeur]],2,FALSE()),0)) -> 1
J131: Bibliothèque_FE | K131: Puissance électrique d'un GPU pour l'embedding | L131: kW | M131: =(IFERROR(VLOOKUP($K$131,Tableau2[[Variable]:[Valeur]],2,FALSE()),0)) -> 0.7
J132: Enrichissement (hors périmètre Ecologits) | K132: ÉLECTRICITÉ consommée par le serveur pour l'embedding | L132: kWh | M132: =IF($M$127>0,(M$126/3600)*(($M$131+($M$195/$M$133))*$M$130),0) -> 3989.3334
J133: Bibliothèque_FE | K133: Nombre de GPU par serveur | L133: unité(s) | M133: =IFERROR(_xlfn.XLOOKUP($K$133,Tableau2[Variable],Tableau2[Valeur]),0) -> 8
...

Sheet Bibliothèque_FE
A1: Catégorie | B1: Sous-catégorie | C1: Variable | D1: Valeur | E1: Unité | F1: Source | G1: MAJ | H1: Commentaire | I1: Valeur historique1 | J1: Source1 | K1: Historique | L1: Source Historique
A2: Bâtiment | B2: Embarqué | C2: Facteur d'émission du batiment et de l'environnement technique | D2: 0.01 | E2: kgCO2eq / kWh | F2: Hubblo (RCP ADEME) | G2: 46111
A3: Eau | B3: Monde | C3: WUE off site - eau utilisée pour produire l'électricité consommée | D3: 3.6737 | E3: L eq | F3: Uptime Inst. 2023 | G3: 46111 | H3: Li et al. (2025)
A4: Eau | B4: CF_Aware | C4: CF_Aware | D4: 1.4 | E4: - | F4: Aware Database | G4: 46111
A5: Electricité | B5: France | C5: Facteur d'émission de l'électricité consommée France | D5: =4.61*10^(-2) -> 0.0461 | E5: kgCO2eq / kWh | F5: Ademe | G5: 46125 | H5: Electricité/2025 - mix moyen/consommation - FR continentale | K5: 0.04418 | L5: Ecologits - ADEME
A6: Electricité | B6: Autre (monde) | C6: Facteur d'émission de l'électricité consommée Monde | D6: 0.458 | E6: kgCO2eq / kWh | F6: Our World in Data | G6: 46113
A7: Embedding | B7: Electricité | C7: Puissance électrique d'un GPU pour l'embedding | D7: 0.7 | E7: kW | F7: Ecologits v0.9 | G7: 46113 | H7: NVIDIA H100 80GB SXM5
A8: Embedding | B8: Configuration | C8: Nombre de GPU utilisé pour l'embedding | D8: 1 | E8: GPU | F8: SNCF | G8: 46113
A9: Entrainement | B9: Embarqué | C9: GES embarqué du stockage HDD de l'entrainement | D9: =1043-402.5 -> 640.5 | E9: kgCO2eq | F9: Resilio DB 03/2026 | G9: 46112 | H9: Seagate Exos 30 TB - a6732f1d11a526d6818449833d73a613672d54918ad5112c0b4b4c077de485b6
A10: Entrainement | B10: Electricité | C10: Puissance électrique du HDD pour le stockage dataset de l'entrainement | D10: =9.5/1000 -> 0.0095 | E10: kW | F10: Kitguru | G10: 46113 | H10: Seagate Exos 30 TB
A11: Entrainement | B11: Durée de vie | C11: Durée d'entrainement | D11: 100 | E11: jours | F11: Epoch.AI | G11: 46113 | H11: Article Epoch.Ai
A12: Entrainement | B12: Ratio | C12: Ratio d'usage HDD | D12: 0.2 | E12: - | F12: Epoch.AI | G12: 46113 | H12: AI models EPOCH AI
A13: Entrainement | B13: Durée de vie | C13: Durée de vie du HDD | D13: 5 | E13: ans | F13: SNCF | G13: 46113
A14: Entrainement | B14: Eau | C14: WU du stockage HDD de l'entrainement (WORLD) | D14: =AVERAGE(270.48-1.07*10^2)*1000 -> 163480 | E14: L eq | F14: Resilio DB 04/2026 | G14: 46136 | H14: Seagate Exos 30 TB - a6732f1d11a526d6818449833d73a613672d54918ad5112c0b4b4c077de485b6
A15: GPU | B15: Configuration | C15: Nombre de GPU par serveur | D15: 8 | E15: GPU | F15: Ecologits v0.9 | G15: 46111
A16: GPU | B16: Durée de vie | C16: Durée de vie d'un GPU | D16: 3 | E16: ans | F16: Ecologits v0.9 | G16: 46111 | J16: Ostrouchov et al. (2020)
A17: GPU | B17: Configuration | C17: Quantification | D17: 16 | E17: Bits | F17: Ecologits v0.9 | G17: 46111
A18: GPU | B18: Configuration | C18: Mémoire GPU | D18: 80 | E18: Go | F18: Ecologits v0.9 | G18: 46111 | H18: NVIDIA H100 80GB HBM3 | J18: Lees-Perasso et al. (2026)
A19: GPU | B19: Energie | C19: GPU_Energy_α | D19: =1.16652731704519*10^(-6) -> 1.1665273e-06 | E19: Wh/tok/Mds | F19: Ecologits v0.9 | G19: 46111
A20: GPU | B20: Energie | C20: GPU_Energy_β | D20: =-0.0112059210255791 -> -0.011205921 | E20: Wh/tok | F20: Ecologits v0.9 | G20: 46111
A21: GPU | B21: Energie | C21: GPU_Energy_γ | D21: =4.052928146734*10^(-5) -> 4.0529281e-05 | E21: Wh | F21: Ecologits v0.9 | G21: 46111
A22: GPU | B22: Configuration | C22: Batch | D22: 64 | E22: nombre de requête | F22: Ecologits v0.9 | G22: 46111
A23: GPU | B23: Latence | C23: Latence_α | D23: 0.00067850881 | E23: s/tok/Mds | F23: Ecologits v0.9 | G23: 46111
A24: GPU | B24: Latence | C24: Latence_β | D24: 0.00031193103 | E24: s/tok | F24: Ecologits v0.9 | G24: 46111
A25: GPU | B25: Latence | C25: Latence_γ | D25: 0.019473718 | E25: s | F25: Ecologits v0.9 | G25: 46111
A26: GPU | B26: Embarqué | C26: GES embarqué d'un seul GPU | D26: 366.54 | E26: kgCO2eq | F26: Resilio DB 03/2026 | G26: 46111 | H26: NVIDIA H100 80GB SXM5 - c5c38823a29224c78a48b7fd33c77b47fcfb74a4655ae68a0de9002f1fa301be | I26: 273 | J26: Ecologits v0.10 - NVIDIA H100 80GB HBM3 - Lees-Perasso et al. (2026) | K26: 164 | L26: Falk et al. 2025
A27: GPU | B27: Eau | C27: WU d'un seul GPU (embarqué) | D27: =101.5*1000 -> 101500 | E27: L eq | F27: Resilio DB 04/2026 | G27: 46136 | H27: NVIDIA H100 80GB SXM5 - c5c38823a29224c78a48b7fd33c77b47fcfb74a4655ae68a0de9002f1fa301be
A28: Inférence | B28: Ratio | C28: Ratio d'inférence sur la compute capacity | D28: 0.8 | F28: SNCF | G28: 46136
A29: Réseau | B29: Electricité | C29: Puissance électrique des pares-feux | D29: 0.09 | E29: kW | F29: Ademe | G29: 46111
A30: Réseau | B30: Ratio | C30: Ratio d'usage pares-feux | D30: 0.0358 | E30: - | F30: ADEME - ARCEP | G30: 46111
A31: Réseau | B31: Electricité | C31: Puissance électrique des routeurs | D31: 0.09 | E31: kW | F31: Ademe | G31: 46111
A32: Réseau | B32: Ratio | C32: Ratio d'usage routeurs | D32: 0.286 | E32: - | F32: ADEME - ARCEP | G32: 46111
A33: Réseau | B33: Electricité | C33: Puissance électrique des switches | D33: 0.09 | E33: kW | F33: Ademe | G33: 46111
A34: Réseau | B34: Ratio | C34: Ratio d'usage switches | D34: 1.468 | F34: ADEME - ARCEP | G34: 46111
A35: Réseau | B35: Durée de vie | C35: Durée de vie équipements réseau | D35: 5 | E35: ans | F35: Ademe | G35: 46111
A36: Réseau | B36: Embarqué | C36: GES embarqué du pare-feu | D36: =1073-739.2 -> 333.8 | E36: kgCO2eq | F36: Resilio DB 03/2026 | G36: 46111 | H36: Fortinet FortiGate 100E Firewall - 2bc89e4b2064dba552275a82c26df6c6400edb6442592ebd8d86cbb42cb9af90 | K36: 391 | L36: Hubblo (RCP Ademe)
A37: Réseau | B37: Eau | C37: WU du pare-feu (FR) | D37: =(1315.55-1.22*10^3)*1000 -> 95550 | E37: L eq | F37: Resilio DB 03/2026 | G37: 46111 | H37: Fortinet FortiGate 100E Firewall - 2bc89e4b2064dba552275a82c26df6c6400edb6442592ebd8d86cbb42cb9af90
A38: Réseau | B38: Embarqué | C38: GES embarqué du routeur | D38: =2439-2036 -> 403 | E38: kgCO2eq | F38: Resilio DB 03/2026 | G38: 46111 | H38: Juniper PTX10002‑36QDD - ae4208b57522c4e79278b460a4c1e4875bdb1edd594698d575c7722ee96e4ffb | K38: 391 | L38: Hubblo (RCP Ademe)
A39: Réseau | B39: Eau | C39: WU du routeur (FR) | D39: =(3484.72-3.37*10^3)*1000 -> 114720 | E39: L eq | F39: Resilio DB 03/2026 | G39: 46111 | H39: Juniper PTX10002‑36QDD - ae4208b57522c4e79278b460a4c1e4875bdb1edd594698d575c7722ee96e4ffb
A40: Réseau | B40: Embarqué | C40: GES embarqué du switch | D40: =1633-1270 -> 363 | E40: kgCO2eq | F40: Resilio DB 03/2026 | G40: 46111 | H40: Arista 7050TX3-48C8 - bd728dcdba0474ed95ff155182665f5bec3fda22a25a9bb0da8c560a63fb33ae | K40: 391 | L40: Hubblo (RCP Ademe)
A41: Réseau | B41: Eau | C41: WU du switch (FR) | D41: =(2203.41-2.1*10^3)*1000 -> 103410 | E41: L eq | F41: Resilio DB 03/2026 | G41: 46111 | H41: Arista 7050TX3-48C8 - bd728dcdba0474ed95ff155182665f5bec3fda22a25a9bb0da8c560a63fb33ae
A42: Serveur | B42: Electricité | C42: Puissance électrique d'un serveur - hors GPU | D42: 1.2 | E42: kW | F42: Ecologits v0.9 | G42: 46111
A43: Serveur | B43: Embarqué | C43: GES embarqué du serveur | D43: =7670.3-3718 -> 3952.3 | E43: kgCO2eq | F43: Resilio DB 03/2026 | G43: 46111 | H43: p5.48xlarge - 43b1720bdbf5e7a93f28bb2a8b8ba3cee234e9fea8972b30aaa782b700f896c4 | K43: 5700 | L43: Ecologits
A44: Serveur | B44: Durée de vie | C44: Durée de vie du serveur | D44: 3 | E44: ans | F44: Ecologits v0.9 | G44: 46111 | J44: Ostrouchov et al. (2020)
A45: Serveur | B45: Eau | C45: WU du serveur (embarqué) | D45: =(7570.63-6.03*10^3)*1000 -> 1540630 | E45: L eq | F45: Resilio DB 04/2026 | G45: 46136 | H45: p5.48xlarge - 43b1720bdbf5e7a93f28bb2a8b8ba3cee234e9fea8972b30aaa782b700f896c4
A46: Front applicatif - pré & post traitements | B46: Estimation | C46: Nombre de tokens de sortie annuels des requêtes traitées par un nœud pour le front | D46: =1600000000 -> 1600000000 | E46: tokens de sortie mensuel | F46: SNCF | G46: 46136 | H46: Hypothèse
A47: Front applicatif - pré & post traitements | B47: Embarqué | C47: GES embarqué d'un nœud 16Go | D47: =(42.13-2.22*10^1) -> 19.93 | E47: kgCO2eq | F47: Resilio DB 04/2026 | G47: 46113 | H47: 16 Go, avec 1,1 PUE et 6 ans de durée de vie, 4vCPU
A48: Front applicatif - pré & post traitements | B48: Eau | C48: WU d'un noeud 16Go | D48: =(4.357*10^1-3.63*10^1)*1000 -> 7270 | E48: L eq | F48: Resilio DB 04/2026 | G48: 46136 | H48: 16 Go, avec 1,1 PUE et 6 ans de durée de vie, 4vCPU
A49: Front applicatif - pré & post traitements | B49: Configuration | C49: Nombre de nœuds | D49: 1 | E49: nœuds | F49: SNCF | G49: 46113 | H49: Hypothèse
A50: Front applicatif - pré & post traitements | B50: Electricité | C50: Puissance électrique d'un nœud | D50: =14.3621390739041/1000 -> 0.014362139 | E50: kW | F50: Resilio DB 04/2026 | G50: 46113 | H50: 16 Go, avec 1,1 PUE et 6 ans de durée de vie, 4vCPU
A51: Front applicatif - pré & post traitements | B51: Durée de vie | C51: Durée de vie d'un nœud 16Go | D51: 4 | E51: ans | F51: SNCF | G51: 46108 | H51: Hypothèse
A52: Token | B52: Estimation | C52: Moyenne de token de sortie par requête | D52: 1000 | E52: tokens de sortie par requête | F52: SNCF | G52: 46111 | H52: Hypothèse | K52: 200
A53: Token | B53: Estimation | C53: Moyenne de token d'entrée par requête | D53: 5000 | E53: tokens d'entrée par requête | F53: SNCF | G53: 46112 | H53: Hypothèse
A54: Electricité | B54: Europe (UE27) | C54: Facteur d'émission de l'électricité consommée Europe (UE27) | D54: =0.2099 -> 0.2099 | E54: kgCO2eq / kWh | F54: Our World in Data | G54: 46266
A55: Electricité | B55: USA | C55: Facteur d'émission de l'électricité consommée USA | D55: 0.3844 | E55: kgCO2eq / kWh | F55: Our World In Data | G55: 46266
A56: Electricité | B56: UK | C56: Facteur d'émission de l'électricité consommée UK | D56: 0.21741 | E56: kgCO2eq / kWh | F56: Our World In Data | G56: 46266
A57: Electricité | B57: Allemagne | C57: Facteur d'émission de l'électricité consommée Allemagne | D57: 0.32965 | E57: kgCO2eq / kWh | F57: Our World In Data | G57: 46266
A58: Electricité | B58: Irlande | C58: Facteur d'émission de l'électricité consommée Irlande | D58: 0.25654 | E58: kgCO2eq / kWh | F58: Our World In Data | G58: 46266
A59: Electricité | B59: Pays Bas | C59: Facteur d'émission de l'électricité consommée Pays Bas | D59: 0.25356 | E59: kgCO2eq / kWh | F59: Our World In Data | G59: 46266
A60: Electricité | B60: Suède | C60: Facteur d'émission de l'électricité consommée Suède | D60: =3.329*10^(-2) -> 0.03329 | E60: kgCO2eq / kWh | F60: Our World in Data | G60: 46266

Sheet Modèles_IA
A1: SNCF | B1: Fournisseurs | C1: Nom du modèle | D1: Catégorie | E1: Architecture | F1: P_total (Mds) | G1: P_total_min | H1: P_total_max | I1: P_active_min (Mds) | J1: P_active_max (Mds) | K1: Sources | L1: Localisation | M1: PUE | N1: Source PUE | O1: WUE on-site - eau utilisée directement dans le centre de donnée | P1: Source WUE | Q1: P_total | R1: P_active_moyenne | S1: Average TPS | T1: Average TTFT | U1: Coefficient | V1: Estimation du nombre de requêtes par jour (par fournisseurs) | W1: Source | X1: Energie consommée pour un FLOP | Y1: Nombre de tokens à l'entrainement | Z1: Date de publication | AA1: Source2 | AB1: Active_model | AC1: Compute Capacity (kW) | AD1: Source Compute
A2: Oui | B2: Anthropic | C2: Claude Haiku 3 | D2: Moyen | E2: MoE | F2: 300 | I2: 30 | J2: 90 | K2: ['https://docs.anthropic.com/en/docs/about-claude/models'] | L2: USA | M2: =AVERAGE(1.09,1.14) -> 1.115 | N2: "- 1.09 for Google in 2024, average of US data centers (https://www.gstatic.com/gumdrop/sustainability/google-2025-environmental-report.pdf) - 1.14 for AWS in 2024 (https://sustainability.aboutamazon.com/products-services/aws-cloud)" | O2: =AVERAGE(0.13,0.99) -> 0.56 | P2: "- 0.13 for AWS in 2024 (https://sustainability.aboutamazon.com/products-services/aws-cloud) - 0.999 for Google in 2024 (https://www.gstatic.com/gumdrop/sustainability/google-2025-environmental-report.pdf)" | Q2: =IF( NOT(ISBLANK(F2)), F2, IF( AND(NOT(ISBLANK(G2)), NOT(ISBLANK(H2))), INT(AVERAGE(G2, H2)), "" ) ) -> 300 | R2: =IF( NOT(ISBLANK(I2)), INT(AVERAGE(I2,J2)), IF( AND(NOT(ISBLANK(G2)), NOT(ISBLANK(H2))), INT(AVERAGE(G2, H2)), "" ) ) -> 60 | S2: 74.2 | T2: 0.53 | U2: =0.062*(Tableau1[[#This Row],[Average TTFT]]/0.44) -> 0.074681818 | V2: =1000000000 -> 1000000000 | W2: https://www.demandsage.com/claude-ai-statistics/ | X2: =2.25*(10^12) -> 2250000000000 | Y2: =1500*(1-EXP(-(Tableau1[[#This Row],[P_total]]^2)/1000))*Tableau1[[#This Row],[P_total]]*10^9 -> 450000000000000 | Z2: 45358 | AA2: Claude | AB2: =IF(Tableau1[[#This Row],[Date de publication]]>=EDATE(TODAY(),-24),"Oui","Non") -> Non | AC2: 1400000 | AD2: https://wccftech.com/openai-sets-goal-to-scale-up-ai-compute-capacity-to-a-whopping-30gw-by-2030/
A3: Oui | B3: Anthropic | C3: Claude Haiku 4.5 | D3: Moyen | E3: Dense | G3: 10 | H3: 35 | K3: ['https://docs.anthropic.com/en/docs/about-claude/models'] | L3: USA | M3: =AVERAGE(1.09,1.14) -> 1.115 | N3: "- 1.09 for Google in 2024, average of US data centers (https://www.gstatic.com/gumdrop/sustainability/google-2025-environmental-report.pdf) - 1.14 for AWS in 2024 (https://sustainability.aboutamazon.com/products-services/aws-cloud)" | O3: =AVERAGE(0.13,0.99) -> 0.56 | P3: "- 0.13 for AWS in 2024 (https://sustainability.aboutamazon.com/products-services/aws-cloud) - 0.999 for Google in 2024 (https://www.gstatic.com/gumdrop/sustainability/google-2025-environmental-report.pdf)" | Q3: =IF( NOT(ISBLANK(F3)), F3, IF( AND(NOT(ISBLANK(G3)), NOT(ISBLANK(H3))), INT(AVERAGE(G3, H3)), "" ) ) -> 22 | R3: =IF( NOT(ISBLANK(I3)), INT(AVERAGE(I3,J3)), IF( AND(NOT(ISBLANK(G3)), NOT(ISBLANK(H3))), INT(AVERAGE(G3, H3)), "" ) ) -> 22 | S3: 70 | T3: 0.67 | U3: =0.062*(Tableau1[[#This Row],[Average TTFT]]/0.44) -> 0.094409091 | V3: 1000000000 | W3: https://www.demandsage.com/claude-ai-statistics/ | X3: =2.25*(10^12) -> 2250000000000 | Y3: =1500*(1-EXP(-(Tableau1[[#This Row],[P_total]]^2)/1000))*Tableau1[[#This Row],[P_total]]*10^9 -> 1.2661664e+13 | Z3: 45945 | AA3: Epoch Ai | AB3: =IF(Tableau1[[#This Row],[Date de publication]]>=EDATE(TODAY(),-24),"Oui","Non") -> Oui | AC3: 1400000 | AD3: https://wccftech.com/openai-sets-goal-to-scale-up-ai-compute-capacity-to-a-whopping-30gw-by-2030/
A4: Oui | B4: Anthropic | C4: Claude Sonnet 3.7 | D4: Moyen | E4: MoE | F4: 440 | I4: 44 | J4: 132 | K4: ['https://docs.anthropic.com/en/docs/about-claude/models'] | L4: USA | M4: =AVERAGE(1.09,1.14) -> 1.115 | N4: "- 1.09 for Google in 2024, average of US data centers (https://www.gstatic.com/gumdrop/sustainability/google-2025-environmental-report.pdf) - 1.14 for AWS in 2024 (https://sustainability.aboutamazon.com/products-services/aws-cloud)" | O4: =AVERAGE(0.13,0.99) -> 0.56 | P4: "- 0.13 for AWS in 2024 (https://sustainability.aboutamazon.com/products-services/aws-cloud) - 0.999 for Google in 2024 (https://www.gstatic.com/gumdrop/sustainability/google-2025-environmental-report.pdf)" | Q4: =IF( NOT(ISBLANK(F4)), F4, IF( AND(NOT(ISBLANK(G4)), NOT(ISBLANK(H4))), INT(AVERAGE(G4, H4)), "" ) ) -> 440 | R4: =IF( NOT(ISBLANK(I4)), INT(AVERAGE(I4,J4)), IF( AND(NOT(ISBLANK(G4)), NOT(ISBLANK(H4))), INT(AVERAGE(G4, H4)), "" ) ) -> 88 | S4: 46 | T4: 1.31 | U4: =0.062*(Tableau1[[#This Row],[Average TTFT]]/0.44) -> 0.18459091 | V4: 1000000000 | W4: https://www.demandsage.com/claude-ai-statistics/ | X4: =2.25*(10^12) -> 2250000000000 | Y4: =1500*(1-EXP(-(Tableau1[[#This Row],[P_total]]^2)/1000))*Tableau1[[#This Row],[P_total]]*10^9 -> 660000000000000 | Z4: 45712 | AA4: Epoch Ai | AB4: =IF(Tableau1[[#This Row],[Date de publication]]>=EDATE(TODAY(),-24),"Oui","Non") -> Oui | AC4: 1400000 | AD4: https://wccftech.com/openai-sets-goal-to-scale-up-ai-compute-capacity-to-a-whopping-30gw-by-2030/
A5: Oui | B5: Anthropic | C5: Claude Sonnet 4 | D5: Grand | E5: MoE | F5: 440 | I5: 44 | J5: 132 | K5: ['https://docs.anthropic.com/en/docs/about-claude/models'] | L5: USA | M5: =AVERAGE(1.09,1.14) -> 1.115 | N5: "- 1.09 for Google in 2024, average of US data centers (https://www.gstatic.com/gumdrop/sustainability/google-2025-environmental-report.pdf) - 1.14 for AWS in 2024 (https://sustainability.aboutamazon.com/products-services/aws-cloud)" | O5: =AVERAGE(0.13,0.99) -> 0.56 | P5: "- 0.13 for AWS in 2024 (https://sustainability.aboutamazon.com/products-services/aws-cloud) - 0.999 for Google in 2024 (https://www.gstatic.com/gumdrop/sustainability/google-2025-environmental-report.pdf)" | Q5: =IF( NOT(ISBLANK(F5)), F5, IF( AND(NOT(ISBLANK(G5)), NOT(ISBLANK(H5))), INT(AVERAGE(G5, H5)), "" ) ) -> 440 | R5: =IF( NOT(ISBLANK(I5)), INT(AVERAGE(I5,J5)), IF( AND(NOT(ISBLANK(G5)), NOT(ISBLANK(H5))), INT(AVERAGE(G5, H5)), "" ) ) -> 88 | S5: 50 | T5: 1.31 | U5: =0.062*(Tableau1[[#This Row],[Average TTFT]]/0.44) -> 0.18459091 | V5: 1000000000 | W5: https://www.demandsage.com/claude-ai-statistics/ | X5: =2.25*(10^12) -> 2250000000000 | Y5: =1500*(1-EXP(-(Tableau1[[#This Row],[P_total]]^2)/1000))*Tableau1[[#This Row],[P_total]]*10^9 -> 660000000000000 | Z5: 45799 | AA5: Epoch Ai | AB5: =IF(Tableau1[[#This Row],[Date de publication]]>=EDATE(TODAY(),-24),"Oui","Non") -> Oui | AC5: 1400000 | AD5: https://wccftech.com/openai-sets-goal-to-scale-up-ai-compute-capacity-to-a-whopping-30gw-by-2030/
A6: Oui | B6: Anthropic | C6: Claude Sonnet 4.5 | D6: Grand | E6: MoE | F6: 440 | I6: 44 | J6: 132 | K6: ['https://docs.anthropic.com/en/docs/about-claude/models'] | L6: USA | M6: =AVERAGE(1.09,1.14) -> 1.115 | N6: "- 1.09 for Google in 2024, average of US data centers (https://www.gstatic.com/gumdrop/sustainability/google-2025-environmental-report.pdf) - 1.14 for AWS in 2024 (https://sustainability.aboutamazon.com/products-services/aws-cloud)" | O6: =AVERAGE(0.13,0.99) -> 0.56 | P6: "- 0.13 for AWS in 2024 (https://sustainability.aboutamazon.com/products-services/aws-cloud) - 0.999 for Google in 2024 (https://www.gstatic.com/gumdrop/sustainability/google-2025-environmental-report.pdf)" | Q6: =IF( NOT(ISBLANK(F6)), F6, IF( AND(NOT(ISBLANK(G6)), NOT(ISBLANK(H6))), INT(AVERAGE(G6, H6)), "" ) ) -> 440 | R6: =IF( NOT(ISBLANK(I6)), INT(AVERAGE(I6,J6)), IF( AND(NOT(ISBLANK(G6)), NOT(ISBLANK(H6))), INT(AVERAGE(G6, H6)), "" ) ) -> 88 | S6: 36 | T6: 1.63 | U6: =0.062*(Tableau1[[#This Row],[Average TTFT]]/0.44) -> 0.22968182 | V6: 1000000000 | W6: https://www.demandsage.com/claude-ai-statistics/ | X6: =2.25*(10^12) -> 2250000000000 | Y6: =1500*(1-EXP(-(Tableau1[[#This Row],[P_total]]^2)/1000))*Tableau1[[#This Row],[P_total]]*10^9 -> 660000000000000 | Z6: 45929 | AA6: Epoch Ai | AB6: =IF(Tableau1[[#This Row],[Date de publication]]>=EDATE(TODAY(),-24),"Oui","Non") -> Oui | AC6: 1400000 | AD6: https://wccftech.com/openai-sets-goal-to-scale-up-ai-compute-capacity-to-a-whopping-30gw-by-2030/
A7: Non | B7: Anthropic | C7: Claude Sonnet 4.6 | D7: Grand | E7: MoE | F7: 440 | I7: 44 | J7: 132 | K7: ['https://docs.anthropic.com/en/docs/about-claude/models'] | L7: USA | M7: =AVERAGE(1.09,1.14) -> 1.115 | N7: "- 1.09 for Google in 2024, average of US data centers (https://www.gstatic.com/gumdrop/sustainability/google-2025-environmental-report.pdf) - 1.14 for AWS in 2024 (https://sustainability.aboutamazon.com/products-services/aws-cloud)" | O7: =AVERAGE(0.13,0.99) -> 0.56 | P7: "- 0.13 for AWS in 2024 (https://sustainability.aboutamazon.com/products-services/aws-cloud) - 0.999 for Google in 2024 (https://www.gstatic.com/gumdrop/sustainability/google-2025-environmental-report.pdf)" | Q7: =IF( NOT(ISBLANK(F7)), F7, IF( AND(NOT(ISBLANK(G7)), NOT(ISBLANK(H7))), INT(AVERAGE(G7, H7)), "" ) ) -> 440 | R7: =IF( NOT(ISBLANK(I7)), INT(AVERAGE(I7,J7)), IF( AND(NOT(ISBLANK(G7)), NOT(ISBLANK(H7))), INT(AVERAGE(G7, H7)), "" ) ) -> 88 | S7: 41 | T7: 1.68 | U7: =0.062*(Tableau1[[#This Row],[Average TTFT]]/0.44) -> 0.23672727 | V7: 1000000000 | W7: https://www.demandsage.com/claude-ai-statistics/ | X7: =2.25*(10^12) -> 2250000000000 | Y7: =1500*(1-EXP(-(Tableau1[[#This Row],[P_total]]^2)/1000))*Tableau1[[#This Row],[P_total]]*10^9 -> 660000000000000 | Z7: 46070 | AA7: Claude | AB7: =IF(Tableau1[[#This Row],[Date de publication]]>=EDATE(TODAY(),-24),"Oui","Non") -> Oui | AC7: 1400000 | AD7: https://wccftech.com/openai-sets-goal-to-scale-up-ai-compute-capacity-to-a-whopping-30gw-by-2030/
A8: Non | B8: Anthropic | C8: Claude Opus 4.6 | D8: Grand | E8: MoE | F8: 670 | I8: 67 | J8: 200 | K8: ['https://docs.anthropic.com/en/docs/about-claude/models'] | L8: USA | M8: =AVERAGE(1.09,1.14) -> 1.115 | N8: "- 1.09 for Google in 2024, average of US data centers (https://www.gstatic.com/gumdrop/sustainability/google-2025-environmental-report.pdf) - 1.14 for AWS in 2024 (https://sustainability.aboutamazon.com/products-services/aws-cloud)" | O8: =AVERAGE(0.13,0.99) -> 0.56 | P8: "- 0.13 for AWS in 2024 (https://sustainability.aboutamazon.com/products-services/aws-cloud) - 0.999 for Google in 2024 (https://www.gstatic.com/gumdrop/sustainability/google-2025-environmental-report.pdf)" | Q8: =IF( NOT(ISBLANK(F8)), F8, IF( AND(NOT(ISBLANK(G8)), NOT(ISBLANK(H8))), INT(AVERAGE(G8, H8)), "" ) ) -> 670 | R8: =IF( NOT(ISBLANK(I8)), INT(AVERAGE(I8,J8)), IF( AND(NOT(ISBLANK(G8)), NOT(ISBLANK(H8))), INT(AVERAGE(G8, H8)), "" ) ) -> 133 | S8: 33.2 | T8: 2.45 | U8: =0.062*(Tableau1[[#This Row],[Average TTFT]]/0.44) -> 0.34522727 | V8: 1000000000 | W8: https://www.demandsage.com/claude-ai-statistics/ | X8: =2.25*(10^12) -> 2250000000000 | Y8: =1500*(1-EXP(-(Tableau1[[#This Row],[P_total]]^2)/1000))*Tableau1[[#This Row],[P_total]]*10^9 -> 1.005e+15 | Z8: 46058 | AA8: AI sister | AB8: =IF(Tableau1[[#This Row],[Date de publication]]>=EDATE(TODAY(),-24),"Oui","Non") -> Oui | AC8: 1400000 | AD8: https://wccftech.com/openai-sets-goal-to-scale-up-ai-compute-capacity-to-a-whopping-30gw-by-2030/
A9: Oui | B9: Google | C9: Gemini 2.5 flash | D9: Moyen | E9: MoE | F9: 440 | I9: 44 | J9: 132 | K9: ['https://ai.google.dev/gemini-api/docs/models'] | L9: USA | M9: 1.09 | N9: "Average for US data centers in 2024 (1.06, 1.11, 1.07, 1.10, 1.06, 1.09, 1.09, 1.10, 1.13, 1.09, 1.08, 1.11, 1.10, 1.10, 1.07, 1.09, 1.16) https://www.gstatic.com/gumdrop/sustainability/google-2025-environmental-report.pdf (page 109)" | O9: 0.99 | P9: "Total data center electricity consumption and water consumption in 2024 are respectively 30,825,600 MWh and 8,135 Million gallons. https://www.gstatic.com/gumdrop/sustainability/google-2025-environmental-report.pdf" | Q9: =IF( NOT(ISBLANK(F9)), F9, IF( AND(NOT(ISBLANK(G9)), NOT(ISBLANK(H9))), INT(AVERAGE(G9, H9)), "" ) ) -> 440 | R9: =IF( NOT(ISBLANK(I9)), INT(AVERAGE(I9,J9)), IF( AND(NOT(ISBLANK(G9)), NOT(ISBLANK(H9))), INT(AVERAGE(G9, H9)), "" ) ) -> 88 | S9: 66.9 | T9: 0.74 | U9: =0.062*(Tableau1[[#This Row],[Average TTFT]]/0.44) -> 0.10427273 | V9: 3000000000 | W9: https://www.technobezz.com/news/google-slashes-free-gemini-api-requests-to-20-per-day-2025-12-20-gl06 | X9: =2.25*(10^12) -> 2250000000000 | Y9: =1500*(1-EXP(-(Tableau1[[#This Row],[P_total]]^2)/1000))*Tableau1[[#This Row],[P_total]]*10^9 -> 660000000000000 | Z9: 45825 | AA9: Google | AB9: =IF(Tableau1[[#This Row],[Date de publication]]>=EDATE(TODAY(),-24),"Oui","Non") -> Oui | AC9: 9000000 | AD9: https://www.cnbc.com/2025/11/21/google-must-double-ai-serving-capacity-every-6-months-to-meet-demand.html
A10: Oui | B10: Google | C10: Gemini 2.5 flash image | D10: Hors catégorie | E10: MoE | F10: 440 | I10: 44 | J10: 132 | K10: ['https://ai.google.dev/gemini-api/docs/models'] | L10: USA | M10: 1.09 | N10: "Average for US data centers in 2024 (1.06, 1.11, 1.07, 1.10, 1.06, 1.09, 1.09, 1.10, 1.13, 1.09, 1.08, 1.11, 1.10, 1.10, 1.07, 1.09, 1.16) https://www.gstatic.com/gumdrop/sustainability/google-2025-environmental-report.pdf (page 109)" | O10: 0.99 | P10: "Total data center electricity consumption and water consumption in 2024 are respectively 30,825,600 MWh and 8,135 Million gallons. https://www.gstatic.com/gumdrop/sustainability/google-2025-environmental-report.pdf" | Q10: =IF( NOT(ISBLANK(F10)), F10, IF( AND(NOT(ISBLANK(G10)), NOT(ISBLANK(H10))), INT(AVERAGE(G10, H10)), "" ) ) -> 440 | R10: =IF( NOT(ISBLANK(I10)), INT(AVERAGE(I10,J10)), IF( AND(NOT(ISBLANK(G10)), NOT(ISBLANK(H10))), INT(AVERAGE(G10, H10)), "" ) ) -> 88 | S10: 110.8 | T10: 5.87 | U10: =0.062*(Tableau1[[#This Row],[Average TTFT]]/0.44) -> 0.82713636 | V10: 3000000000 | W10: https://www.technobezz.com/news/google-slashes-free-gemini-api-requests-to-20-per-day-2025-12-20-gl06 | X10: =2.25*(10^12) -> 2250000000000 | Y10: =1500*(1-EXP(-(Tableau1[[#This Row],[P_total]]^2)/1000))*Tableau1[[#This Row],[P_total]]*10^9 -> 660000000000000 | Z10: 45932 | AA10: Google | AB10: =IF(Tableau1[[#This Row],[Date de publication]]>=EDATE(TODAY(),-24),"Oui","Non") -> Oui | AC10: 9000000 | AD10: https://www.cnbc.com/2025/11/21/google-must-double-ai-serving-capacity-every-6-months-to-meet-demand.html
A11: Non | B11: Google | C11: Gemini 2.5 flash lite | D11: Petit | E11: Dense | G11: 8 | H11: 28 | K11: ['https://ai.google.dev/gemini-api/docs/models'] | L11: USA | M11: 1.09 | N11: "Average for US data centers in 2024 (1.06, 1.11, 1.07, 1.10, 1.06, 1.09, 1.09, 1.10, 1.13, 1.09, 1.08, 1.11, 1.10, 1.10, 1.07, 1.09, 1.16) https://www.gstatic.com/gumdrop/sustainability/google-2025-environmental-report.pdf (page 109)" | O11: 0.99 | P11: "Total data center electricity consumption and water consumption in 2024 are respectively 30,825,600 MWh and 8,135 Million gallons. https://www.gstatic.com/gumdrop/sustainability/google-2025-environmental-report.pdf" | Q11: =IF( NOT(ISBLANK(F11)), F11, IF( AND(NOT(ISBLANK(G11)), NOT(ISBLANK(H11))), INT(AVERAGE(G11, H11)), "" ) ) -> 18 | R11: =IF( NOT(ISBLANK(I11)), INT(AVERAGE(I11,J11)), IF( AND(NOT(ISBLANK(G11)), NOT(ISBLANK(H11))), INT(AVERAGE(G11, H11)), "" ) ) -> 18 | S11: 71.5 | T11: 0.56 | U11: =0.062*(Tableau1[[#This Row],[Average TTFT]]/0.44) -> 0.078909091 | V11: 3000000000 | W11: https://www.technobezz.com/news/google-slashes-free-gemini-api-requests-to-20-per-day-2025-12-20-gl06 | X11: =2.25*(10^12) -> 2250000000000 | Y11: =1500*(1-EXP(-(Tableau1[[#This Row],[P_total]]^2)/1000))*Tableau1[[#This Row],[P_total]]*10^9 -> 7.4722435e+12 | Z11: 45860 | AA11: Google | AB11: =IF(Tableau1[[#This Row],[Date de publication]]>=EDATE(TODAY(),-24),"Oui","Non") -> Oui | AC11: 9000000 | AD11: https://www.cnbc.com/2025/11/21/google-must-double-ai-serving-capacity-every-6-months-to-meet-demand.html
A12: Oui | B12: Google | C12: Gemini 2.5 pro | D12: Grand | E12: MoE | F12: 2000 | I12: 200 | J12: 600 | K12: ['https://ai.google.dev/gemini-api/docs/models'] | L12: USA | M12: 1.09 | N12: "Average for US data centers in 2024 (1.06, 1.11, 1.07, 1.10, 1.06, 1.09, 1.09, 1.10, 1.13, 1.09, 1.08, 1.11, 1.10, 1.10, 1.07, 1.09, 1.16) https://www.gstatic.com/gumdrop/sustainability/google-2025-environmental-report.pdf (page 109)" | O12: 0.99 | P12: "Total data center electricity consumption and water consumption in 2024 are respectively 30,825,600 MWh and 8,135 Million gallons. https://www.gstatic.com/gumdrop/sustainability/google-2025-environmental-report.pdf" | Q12: =IF( NOT(ISBLANK(F12)), F12, IF( AND(NOT(ISBLANK(G12)), NOT(ISBLANK(H12))), INT(AVERAGE(G12, H12)), "" ) ) -> 2000 | R12: =IF( NOT(ISBLANK(I12)), INT(AVERAGE(I12,J12)), IF( AND(NOT(ISBLANK(G12)), NOT(ISBLANK(H12))), INT(AVERAGE(G12, H12)), "" ) ) -> 400 | S12: 91.1 | T12: 2.83 | U12: =0.062*(Tableau1[[#This Row],[Average TTFT]]/0.44) -> 0.39877273 | V12: 3000000000 | W12: https://www.technobezz.com/news/google-slashes-free-gemini-api-requests-to-20-per-day-2025-12-20-gl06 | X12: =2.25*(10^12) -> 2250000000000 | Y12: =1500*(1-EXP(-(Tableau1[[#This Row],[P_total]]^2)/1000))*Tableau1[[#This Row],[P_total]]*10^9 -> 3e+15 | Z12: 45637 | AA12: Epoch Ai | AB12: =IF(Tableau1[[#This Row],[Date de publication]]>=EDATE(TODAY(),-24),"Oui","Non") -> Oui | AC12: 9000000 | AD12: https://www.cnbc.com/2025/11/21/google-must-double-ai-serving-capacity-every-6-months-to-meet-demand.html
A13: Oui | B13: Mistral AI | C13: Codestral | D13: Moyen | E13: Dense | G13: 22.25 | H13: 22.25 | K13: ['https://docs.mistral.ai/getting-started/models/', 'https://mistral.ai/news/codestral'] | L13: SW | M13: 1.16 | N13: "Only available for Sweden (Norway data center excluded) https://datacenters.microsoft.com/sustainability/efficiency/" | O13: 0.09 | P13: "Only available for Sweden (Norway data center excluded) https://datacenters.microsoft.com/sustainability/efficiency/" | Q13: =IF( NOT(ISBLANK(F13)), F13, IF( AND(NOT(ISBLANK(G13)), NOT(ISBLANK(H13))), INT(AVERAGE(G13, H13)), "" ) ) -> 22 | R13: =IF( NOT(ISBLANK(I13)), INT(AVERAGE(I13,J13)), IF( AND(NOT(ISBLANK(G13)), NOT(ISBLANK(H13))), INT(AVERAGE(G13, H13)), "" ) ) -> 22 | S13: 54.4 | T13: 0.23 | U13: =0.062*(Tableau1[[#This Row],[Average TTFT]]/0.44) -> 0.032409091 | V13: 40000000 | W13: https://fueler.io/blog/mistral-ai-usage-revenue-valuation-growth-statistics | X13: =2.25*(10^12) -> 2250000000000 | Y13: =1500*(1-EXP(-(Tableau1[[#This Row],[P_total]]^2)/1000))*Tableau1[[#This Row],[P_total]]*10^9 -> 1.2661664e+13 | Z13: 45670 | AA13: Mistral AI | AB13: =IF(Tableau1[[#This Row],[Date de publication]]>=EDATE(TODAY(),-24),"Oui","Non") -> Oui | AC13: 200000 | AD13: https://www.cnbc.com/2026/03/30/mistral-ai-paris-data-center-cluster-debt-financing.html
A14: Oui | B14: Mistral AI | C14: Magistral Medium | D14: Moyen | E14: Dense | G14: 70 | H14: 120 | K14: ['https://docs.mistral.ai/getting-started/models/'] | L14: SW | M14: 1.16 | N14: "Only available for Sweden (Norway data center excluded) https://datacenters.microsoft.com/sustainability/efficiency/" | O14: 0.09 | P14: "Only available for Sweden (Norway data center excluded) https://datacenters.microsoft.com/sustainability/efficiency/" | Q14: =IF( NOT(ISBLANK(F14)), F14, IF( AND(NOT(ISBLANK(G14)), NOT(ISBLANK(H14))), INT(AVERAGE(G14, H14)), "" ) ) -> 95 | R14: =IF( NOT(ISBLANK(I14)), INT(AVERAGE(I14,J14)), IF( AND(NOT(ISBLANK(G14)), NOT(ISBLANK(H14))), INT(AVERAGE(G14, H14)), "" ) ) -> 95 | S14: 48.6 | T14: 0.41 | U14: =0.062*(Tableau1[[#This Row],[Average TTFT]]/0.44) -> 0.057772727 | V14: 40000000 | W14: https://fueler.io/blog/mistral-ai-usage-revenue-valuation-growth-statistics | X14: =2.25*(10^12) -> 2250000000000 | Y14: =1500*(1-EXP(-(Tableau1[[#This Row],[P_total]]^2)/1000))*Tableau1[[#This Row],[P_total]]*10^9 -> 1.4248285e+14 | Z14: 45818 | AA14: Mistral AI | AB14: =IF(Tableau1[[#This Row],[Date de publication]]>=EDATE(TODAY(),-24),"Oui","Non") -> Oui | AC14: 200000 | AD14: https://www.cnbc.com/2026/03/30/mistral-ai-paris-data-center-cluster-debt-financing.html
A15: Oui | B15: Mistral AI | C15: Ministral 3b | D15: Petit | E15: Dense | G15: 3.32 | H15: 3.32 | K15: ['https://docs.mistral.ai/getting-started/models/', 'https://mistral.ai/news/ministraux'] | L15: SW | M15: 1.16 | N15: "Only available for Sweden (Norway data center excluded) https://datacenters.microsoft.com/sustainability/efficiency/" | O15: 0.09 | P15: "Only available for Sweden (Norway data center excluded) https://datacenters.microsoft.com/sustainability/efficiency/" | Q15: =IF( NOT(ISBLANK(F15)), F15, IF( AND(NOT(ISBLANK(G15)), NOT(ISBLANK(H15))), INT(AVERAGE(G15, H15)), "" ) ) -> 3 | R15: =IF( NOT(ISBLANK(I15)), INT(AVERAGE(I15,J15)), IF( AND(NOT(ISBLANK(G15)), NOT(ISBLANK(H15))), INT(AVERAGE(G15, H15)), "" ) ) -> 3 | S15: 65.2 | T15: 0.23 | U15: =0.062*(Tableau1[[#This Row],[Average TTFT]]/0.44) -> 0.032409091 | V15: 40000000 | W15: https://fueler.io/blog/mistral-ai-usage-revenue-valuation-growth-statistics | X15: =2.25*(10^12) -> 2250000000000 | Y15: =1500*(1-EXP(-(Tableau1[[#This Row],[P_total]]^2)/1000))*Tableau1[[#This Row],[P_total]]*10^9 -> 4.0318296e+10 | Z15: 45574 | AA15: Mistral AI | AB15: =IF(Tableau1[[#This Row],[Date de publication]]>=EDATE(TODAY(),-24),"Oui","Non") -> Oui | AC15: 200000 | AD15: https://www.cnbc.com/2026/03/30/mistral-ai-paris-data-center-cluster-debt-financing.html
A16: Oui | B16: Mistral AI | C16: Ministral 8b | D16: Petit | E16: Dense | G16: 8.02 | H16: 8.02 | K16: ['https://docs.mistral.ai/getting-started/models/', 'https://mistral.ai/news/ministraux'] | L16: SW | M16: 1.16 | N16: "Only available for Sweden (Norway data center excluded) https://datacenters.microsoft.com/sustainability/efficiency/" | O16: 0.09 | P16: "Only available for Sweden (Norway data center excluded) https://datacenters.microsoft.com/sustainability/efficiency/" | Q16: =IF( NOT(ISBLANK(F16)), F16, IF( AND(NOT(ISBLANK(G16)), NOT(ISBLANK(H16))), INT(AVERAGE(G16, H16)), "" ) ) -> 8 | R16: =IF( NOT(ISBLANK(I16)), INT(AVERAGE(I16,J16)), IF( AND(NOT(ISBLANK(G16)), NOT(ISBLANK(H16))), INT(AVERAGE(G16, H16)), "" ) ) -> 8 | S16: 87.8 | T16: 0.27 | U16: =0.062*(Tableau1[[#This Row],[Average TTFT]]/0.44) -> 0.038045455 | V16: 40000000 | W16: https://fueler.io/blog/mistral-ai-usage-revenue-valuation-growth-statistics | X16: =2.25*(10^12) -> 2250000000000 | Y16: =1500*(1-EXP(-(Tableau1[[#This Row],[P_total]]^2)/1000))*Tableau1[[#This Row],[P_total]]*10^9 -> 7.4394001e+11 | Z16: 45574 | AA16: Mistral AI | AB16: =IF(Tableau1[[#This Row],[Date de publication]]>=EDATE(TODAY(),-24),"Oui","Non") -> Oui | AC16: 200000 | AD16: https://www.cnbc.com/2026/03/30/mistral-ai-paris-data-center-cluster-debt-financing.html
A17: Oui | B17: Mistral AI | C17: Mistral Large | D17: Grand | E17: Dense | G17: 122.61 | H17: 122.61 | K17: ['https://docs.mistral.ai/getting-started/models/', 'https://mistral.ai/news/mistral-large-2407'] | L17: SW | M17: 1.16 | N17: "Only available for Sweden (Norway data center excluded) https://datacenters.microsoft.com/sustainability/efficiency/" | O17: 0.09 | P17: "Only available for Sweden (Norway data center excluded) https://datacenters.microsoft.com/sustainability/efficiency/" | Q17: =IF( NOT(ISBLANK(F17)), F17, IF( AND(NOT(ISBLANK(G17)), NOT(ISBLANK(H17))), INT(AVERAGE(G17, H17)), "" ) ) -> 122 | R17: =IF( NOT(ISBLANK(I17)), INT(AVERAGE(I17,J17)), IF( AND(NOT(ISBLANK(G17)), NOT(ISBLANK(H17))), INT(AVERAGE(G17, H17)), "" ) ) -> 122 | S17: 35.6 | T17: 0.45 | U17: =0.062*(Tableau1[[#This Row],[Average TTFT]]/0.44) -> 0.063409091 | V17: 40000000 | W17: https://fueler.io/blog/mistral-ai-usage-revenue-valuation-growth-statistics | X17: =2.25*(10^12) -> 2250000000000 | Y17: =1500*(1-EXP(-(Tableau1[[#This Row],[P_total]]^2)/1000))*Tableau1[[#This Row],[P_total]]*10^9 -> 1.8299994e+14 | Z17: 45348 | AA17: Epoch Ai | AB17: =IF(Tableau1[[#This Row],[Date de publication]]>=EDATE(TODAY(),-24),"Oui","Non") -> Non | AC17: 200000 | AD17: https://www.cnbc.com/2026/03/30/mistral-ai-paris-data-center-cluster-debt-financing.html
A18: Oui | B18: Mistral AI | C18: Mistral Medium | D18: Moyen | E18: Dense | G18: 70 | H18: 120 | K18: ['https://docs.mistral.ai/getting-started/models/'] | L18: SW | M18: 1.16 | N18: "Only available for Sweden (Norway data center excluded) https://datacenters.microsoft.com/sustainability/efficiency/" | O18: 0.09 | P18: "Only available for Sweden (Norway data center excluded) https://datacenters.microsoft.com/sustainability/efficiency/" | Q18: =IF( NOT(ISBLANK(F18)), F18, IF( AND(NOT(ISBLANK(G18)), NOT(ISBLANK(H18))), INT(AVERAGE(G18, H18)), "" ) ) -> 95 | R18: =IF( NOT(ISBLANK(I18)), INT(AVERAGE(I18,J18)), IF( AND(NOT(ISBLANK(G18)), NOT(ISBLANK(H18))), INT(AVERAGE(G18, H18)), "" ) ) -> 95 | S18: 45.1 | T18: 0.59 | U18: =0.062*(Tableau1[[#This Row],[Average TTFT]]/0.44) -> 0.083136364 | V18: 40000000 | W18: https://fueler.io/blog/mistral-ai-usage-revenue-valuation-growth-statistics | X18: =2.25*(10^12) -> 2250000000000 | Y18: =1500*(1-EXP(-(Tableau1[[#This Row],[P_total]]^2)/1000))*Tableau1[[#This Row],[P_total]]*10^9 -> 1.4248285e+14 | Z18: 45881 | AA18: Mistral AI | AB18: =IF(Tableau1[[#This Row],[Date de publication]]>=EDATE(TODAY(),-24),"Oui","Non") -> Oui | AC18: 200000 | AD18: https://www.cnbc.com/2026/03/30/mistral-ai-paris-data-center-cluster-debt-financing.html
A19: Oui | B19: Mistral AI | C19: Pixtral Large | D19: Grand | E19: Dense | G19: 123 | H19: 123 | K19: ['https://docs.mistral.ai/getting-started/models/', 'https://mistral.ai/news/pixtral-large'] | L19: SW | M19: 1.16 | N19: "Only available for Sweden (Norway data center excluded) https://datacenters.microsoft.com/sustainability/efficiency/" | O19: 0.09 | P19: "Only available for Sweden (Norway data center excluded) https://datacenters.microsoft.com/sustainability/efficiency/" | Q19: =IF( NOT(ISBLANK(F19)), F19, IF( AND(NOT(ISBLANK(G19)), NOT(ISBLANK(H19))), INT(AVERAGE(G19, H19)), "" ) ) -> 123 | R19: =IF( NOT(ISBLANK(I19)), INT(AVERAGE(I19,J19)), IF( AND(NOT(ISBLANK(G19)), NOT(ISBLANK(H19))), INT(AVERAGE(G19, H19)), "" ) ) -> 123 | S19: 35.6 | T19: 0.45 | U19: =0.062*(Tableau1[[#This Row],[Average TTFT]]/0.44) -> 0.063409091 | V19: 40000000 | W19: https://fueler.io/blog/mistral-ai-usage-revenue-valuation-growth-statistics | X19: =2.25*(10^12) -> 2250000000000 | Y19: =1500*(1-EXP(-(Tableau1[[#This Row],[P_total]]^2)/1000))*Tableau1[[#This Row],[P_total]]*10^9 -> 1.8449995e+14 | Z19: 45614 | AA19: Epoch Ai | AB19: =IF(Tableau1[[#This Row],[Date de publication]]>=EDATE(TODAY(),-24),"Oui","Non") -> Oui | AC19: 200000 | AD19: https://www.cnbc.com/2026/03/30/mistral-ai-paris-data-center-cluster-debt-financing.html
A20: Oui | B20: OpenAI | C20: GPT-4 | D20: Grand | E20: MoE | F20: 1760 | I20: 176 | J20: 528 | K20: https://platform.openai.com/docs/models#gpt-4-turbo-and-gpt-4' | L20: USA | M20: 1.2 | N20: "Average for US data centers in 2023 (1.18, 1.35, 1.16, 1.28, 1.14, 1.15, 1.11) https://datacenters.microsoft.com/sustainability/efficiency/" | O20: 0.569 | P20: "Average for US data centers in 2023 (1.63, 0.74, 0.14, 0.25, 0.14, 0.95, 0.13) https://datacenters.microsoft.com/sustainability/efficiency/" | Q20: =IF( NOT(ISBLANK(F20)), F20, IF( AND(NOT(ISBLANK(G20)), NOT(ISBLANK(H20))), INT(AVERAGE(G20, H20)), "" ) ) -> 1760 | R20: =IF( NOT(ISBLANK(I20)), INT(AVERAGE(I20,J20)), IF( AND(NOT(ISBLANK(G20)), NOT(ISBLANK(H20))), INT(AVERAGE(G20, H20)), "" ) ) -> 352 | S20: 12.2 | T20: 0.74 | U20: =0.062*(Tableau1[[#This Row],[Average TTFT]]/0.44) -> 0.10427273 | V20: 2000000000 | W20: https://www.feedough.com/openai-statistics/ https://www.demandsage.com/chatgpt-statistics/ | X20: =2.25*(10^12) -> 2250000000000 | Y20: =1500*(1-EXP(-(Tableau1[[#This Row],[P_total]]^2)/1000))*Tableau1[[#This Row],[P_total]]*10^9 -> 2.64e+15 | Z20: 45000 | AA20: Epoch Ai | AB20: =IF(Tableau1[[#This Row],[Date de publication]]>=EDATE(TODAY(),-24),"Oui","Non") -> Non | AC20: 1900000 | AD20: https://finance.yahoo.com/sectors/technology/articles/coreweave-signs-multi-deal-anthropic-162247263.html
A21: Oui | B21: OpenAI | C21: GPT-4 turbo | D21: Grand | E21: MoE | F21: 880 | I21: 88 | J21: 264 | K21: https://platform.openai.com/docs/models#gpt-4-turbo-and-gpt-4' | L21: USA | M21: 1.2 | N21: "Average for US data centers in 2023 (1.18, 1.35, 1.16, 1.28, 1.14, 1.15, 1.11) https://datacenters.microsoft.com/sustainability/efficiency/" | O21: 0.569 | P21: "Average for US data centers in 2023 (1.63, 0.74, 0.14, 0.25, 0.14, 0.95, 0.13) https://datacenters.microsoft.com/sustainability/efficiency/" | Q21: =IF( NOT(ISBLANK(F21)), F21, IF( AND(NOT(ISBLANK(G21)), NOT(ISBLANK(H21))), INT(AVERAGE(G21, H21)), "" ) ) -> 880 | R21: =IF( NOT(ISBLANK(I21)), INT(AVERAGE(I21,J21)), IF( AND(NOT(ISBLANK(G21)), NOT(ISBLANK(H21))), INT(AVERAGE(G21, H21)), "" ) ) -> 176 | S21: 23.6 | T21: 1.02 | U21: =0.062*(Tableau1[[#This Row],[Average TTFT]]/0.44) -> 0.14372727 | V21: 2000000000 | W21: https://www.feedough.com/openai-statistics/ https://www.demandsage.com/chatgpt-statistics/ | X21: =2.25*(10^12) -> 2250000000000 | Y21: =1500*(1-EXP(-(Tableau1[[#This Row],[P_total]]^2)/1000))*Tableau1[[#This Row],[P_total]]*10^9 -> 1.32e+15 | Z21: 45602 | AA21: Epoch Ai | AB21: =IF(Tableau1[[#This Row],[Date de publication]]>=EDATE(TODAY(),-24),"Oui","Non") -> Oui | AC21: 2000000 | AD21: https://finance.yahoo.com/sectors/technology/articles/coreweave-signs-multi-deal-anthropic-162247263.html
A22: Oui | B22: OpenAI | C22: GPT-4.1 | D22: Moyen | E22: MoE | F22: 352 | I22: 35 | J22: 106 | K22: https://platform.openai.com/docs/models' | L22: USA | M22: 1.2 | N22: "Average for US data centers in 2023 (1.18, 1.35, 1.16, 1.28, 1.14, 1.15, 1.11) https://datacenters.microsoft.com/sustainability/efficiency/" | O22: 0.569 | P22: "Average for US data centers in 2023 (1.63, 0.74, 0.14, 0.25, 0.14, 0.95, 0.13) https://datacenters.microsoft.com/sustainability/efficiency/" | Q22: =IF( NOT(ISBLANK(F22)), F22, IF( AND(NOT(ISBLANK(G22)), NOT(ISBLANK(H22))), INT(AVERAGE(G22, H22)), "" ) ) -> 352 | R22: =IF( NOT(ISBLANK(I22)), INT(AVERAGE(I22,J22)), IF( AND(NOT(ISBLANK(G22)), NOT(ISBLANK(H22))), INT(AVERAGE(G22, H22)), "" ) ) -> 70 | S22: 44.2 | T22: 0.73 | U22: =0.062*(Tableau1[[#This Row],[Average TTFT]]/0.44) -> 0.10286364 | V22: 2000000000 | W22: https://www.feedough.com/openai-statistics/ https://www.demandsage.com/chatgpt-statistics/ | X22: =2.25*(10^12) -> 2250000000000 | Y22: =1500*(1-EXP(-(Tableau1[[#This Row],[P_total]]^2)/1000))*Tableau1[[#This Row],[P_total]]*10^9 -> 528000000000000 | Z22: 45791 | AA22: Open Ai | AB22: =IF(Tableau1[[#This Row],[Date de publication]]>=EDATE(TODAY(),-24),"Oui","Non") -> Oui | AC22: 2000000 | AD22: https://finance.yahoo.com/sectors/technology/articles/coreweave-signs-multi-deal-anthropic-162247263.html
A23: Oui | B23: OpenAI | C23: GPT-4.1 nano | D23: Petit | E23: Dense | G23: 10 | H23: 37 | K23: https://platform.openai.com/docs/models' | L23: USA | M23: 1.2 | N23: "Average for US data centers in 2023 (1.18, 1.35, 1.16, 1.28, 1.14, 1.15, 1.11) https://datacenters.microsoft.com/sustainability/efficiency/" | O23: 0.569 | P23: "Average for US data centers in 2023 (1.63, 0.74, 0.14, 0.25, 0.14, 0.95, 0.13) https://datacenters.microsoft.com/sustainability/efficiency/" | Q23: =IF( NOT(ISBLANK(F23)), F23, IF( AND(NOT(ISBLANK(G23)), NOT(ISBLANK(H23))), INT(AVERAGE(G23, H23)), "" ) ) -> 23 | R23: =IF( NOT(ISBLANK(I23)), INT(AVERAGE(I23,J23)), IF( AND(NOT(ISBLANK(G23)), NOT(ISBLANK(H23))), INT(AVERAGE(G23, H23)), "" ) ) -> 23 | S23: 55.4 | T23: 0.55 | U23: =0.062*(Tableau1[[#This Row],[Average TTFT]]/0.44) -> 0.0775 | V23: 2000000000 | W23: https://www.feedough.com/openai-statistics/ https://www.demandsage.com/chatgpt-statistics/ | X23: =2.25*(10^12) -> 2250000000000 | Y23: =1500*(1-EXP(-(Tableau1[[#This Row],[P_total]]^2)/1000))*Tableau1[[#This Row],[P_total]]*10^9 -> 1.4172812e+13 | Z23: 45761 | AA23: Microsoft | AB23: =IF(Tableau1[[#This Row],[Date de publication]]>=EDATE(TODAY(),-24),"Oui","Non") -> Oui | AC23: 2000000 | AD23: https://finance.yahoo.com/sectors/technology/articles/coreweave-signs-multi-deal-anthropic-162247263.html
A24: Oui | B24: OpenAI | C24: GPT-4.1-mini | D24: Petit | E24: Dense | G24: 40 | H24: 112 | K24: https://platform.openai.com/docs/models' | L24: USA | M24: 1.2 | N24: "Average for US data centers in 2023 (1.18, 1.35, 1.16, 1.28, 1.14, 1.15, 1.11) https://datacenters.microsoft.com/sustainability/efficiency/" | O24: 0.569 | P24: "Average for US data centers in 2023 (1.63, 0.74, 0.14, 0.25, 0.14, 0.95, 0.13) https://datacenters.microsoft.com/sustainability/efficiency/" | Q24: =IF( NOT(ISBLANK(F24)), F24, IF( AND(NOT(ISBLANK(G24)), NOT(ISBLANK(H24))), INT(AVERAGE(G24, H24)), "" ) ) -> 76 | R24: =IF( NOT(ISBLANK(I24)), INT(AVERAGE(I24,J24)), IF( AND(NOT(ISBLANK(G24)), NOT(ISBLANK(H24))), INT(AVERAGE(G24, H24)), "" ) ) -> 76 | S24: 40.2 | T24: 0.62 | U24: =0.062*(Tableau1[[#This Row],[Average TTFT]]/0.44) -> 0.087363636 | V24: 2000000000 | W24: https://www.feedough.com/openai-statistics/ https://www.demandsage.com/chatgpt-statistics/ | X24: =2.25*(10^12) -> 2250000000000 | Y24: =1500*(1-EXP(-(Tableau1[[#This Row],[P_total]]^2)/1000))*Tableau1[[#This Row],[P_total]]*10^9 -> 1.1364648e+14 | Z24: 45762 | AA24: Microsoft | AB24: =IF(Tableau1[[#This Row],[Date de publication]]>=EDATE(TODAY(),-24),"Oui","Non") -> Oui | AC24: 2000000 | AD24: https://finance.yahoo.com/sectors/technology/articles/coreweave-signs-multi-deal-anthropic-162247263.html
A25: Oui | B25: OpenAI | C25: GPT-4o | D25: Moyen | E25: MoE | F25: 440 | I25: 44 | J25: 132 | K25: https://platform.openai.com/docs/models#gpt-4o' | L25: USA | M25: 1.2 | N25: "Average for US data centers in 2023 (1.18, 1.35, 1.16, 1.28, 1.14, 1.15, 1.11) https://datacenters.microsoft.com/sustainability/efficiency/" | O25: 0.569 | P25: "Average for US data centers in 2023 (1.63, 0.74, 0.14, 0.25, 0.14, 0.95, 0.13) https://datacenters.microsoft.com/sustainability/efficiency/" | Q25: =IF( NOT(ISBLANK(F25)), F25, IF( AND(NOT(ISBLANK(G25)), NOT(ISBLANK(H25))), INT(AVERAGE(G25, H25)), "" ) ) -> 440 | R25: =IF( NOT(ISBLANK(I25)), INT(AVERAGE(I25,J25)), IF( AND(NOT(ISBLANK(G25)), NOT(ISBLANK(H25))), INT(AVERAGE(G25, H25)), "" ) ) -> 88 | S25: 40.2 | T25: 0.54 | U25: =0.062*(Tableau1[[#This Row],[Average TTFT]]/0.44) -> 0.076090909 | V25: 2000000000 | W25: https://www.feedough.com/openai-statistics/ https://www.demandsage.com/chatgpt-statistics/ | X25: =2.25*(10^12) -> 2250000000000 | Y25: =1500*(1-EXP(-(Tableau1[[#This Row],[P_total]]^2)/1000))*Tableau1[[#This Row],[P_total]]*10^9 -> 660000000000000 | Z25: 45616 | AA25: Epoch Ai | AB25: =IF(Tableau1[[#This Row],[Date de publication]]>=EDATE(TODAY(),-24),"Oui","Non") -> Oui | AC25: 2000000 | AD25: https://finance.yahoo.com/sectors/technology/articles/coreweave-signs-multi-deal-anthropic-162247263.html
A26: Oui | B26: OpenAI | C26: GPT-4o mini | D26: Petit | E26: Dense | G26: 8 | H26: 28 | K26: ['https://platform.openai.com/docs/models#gpt-4o-mini'] | L26: USA | M26: 1.2 | N26: "Average for US data centers in 2023 (1.18, 1.35, 1.16, 1.28, 1.14, 1.15, 1.11) https://datacenters.microsoft.com/sustainability/efficiency/" | O26: 0.569 | P26: "Average for US data centers in 2023 (1.63, 0.74, 0.14, 0.25, 0.14, 0.95, 0.13) https://datacenters.microsoft.com/sustainability/efficiency/" | Q26: =IF( NOT(ISBLANK(F26)), F26, IF( AND(NOT(ISBLANK(G26)), NOT(ISBLANK(H26))), INT(AVERAGE(G26, H26)), "" ) ) -> 18 | R26: =IF( NOT(ISBLANK(I26)), INT(AVERAGE(I26,J26)), IF( AND(NOT(ISBLANK(G26)), NOT(ISBLANK(H26))), INT(AVERAGE(G26, H26)), "" ) ) -> 18 | S26: 34.5 | T26: 0.51 | U26: =0.062*(Tableau1[[#This Row],[Average TTFT]]/0.44) -> 0.071863636 | V26: 2000000000 | W26: https://www.feedough.com/openai-statistics/ https://www.demandsage.com/chatgpt-statistics/ | X26: =2.25*(10^12) -> 2250000000000 | Y26: =1500*(1-EXP(-(Tableau1[[#This Row],[P_total]]^2)/1000))*Tableau1[[#This Row],[P_total]]*10^9 -> 7.4722435e+12 | Z26: 45491 | AA26: Epoch Ai | AB26: =IF(Tableau1[[#This Row],[Date de publication]]>=EDATE(TODAY(),-24),"Oui","Non") -> Non | AC26: 2000000 | AD26: https://finance.yahoo.com/sectors/technology/articles/coreweave-signs-multi-deal-anthropic-162247263.html
A27: Oui | B27: OpenAI | C27: GPT-5 | D27: Grand | E27: MoE | F27: 300 | I27: 30 | J27: 90 | K27: https://platform.openai.com/docs/models' | L27: USA | M27: 1.2 | N27: "Average for US data centers in 2023 (1.18, 1.35, 1.16, 1.28, 1.14, 1.15, 1.11) https://datacenters.microsoft.com/sustainability/efficiency/" | O27: 0.569 | P27: "Average for US data centers in 2023 (1.63, 0.74, 0.14, 0.25, 0.14, 0.95, 0.13) https://datacenters.microsoft.com/sustainability/efficiency/" | Q27: =IF( NOT(ISBLANK(F27)), F27, IF( AND(NOT(ISBLANK(G27)), NOT(ISBLANK(H27))), INT(AVERAGE(G27, H27)), "" ) ) -> 300 | R27: =IF( NOT(ISBLANK(I27)), INT(AVERAGE(I27,J27)), IF( AND(NOT(ISBLANK(G27)), NOT(ISBLANK(H27))), INT(AVERAGE(G27, H27)), "" ) ) -> 60 | S27: 46.2 | T27: 13.64 | U27: =0.062*(Tableau1[[#This Row],[Average TTFT]]/0.44) -> 1.922 | V27: 2000000000 | W27: https://www.feedough.com/openai-statistics/ https://www.demandsage.com/chatgpt-statistics/ | X27: =2.25*(10^12) -> 2250000000000 | Y27: =1500*(1-EXP(-(Tableau1[[#This Row],[P_total]]^2)/1000))*Tableau1[[#This Row],[P_total]]*10^9 -> 450000000000000 | Z27: 45876 | AA27: Epoch Ai | AB27: =IF(Tableau1[[#This Row],[Date de publication]]>=EDATE(TODAY(),-24),"Oui","Non") -> Oui | AC27: 2000000 | AD27: https://finance.yahoo.com/sectors/technology/articles/coreweave-signs-multi-deal-anthropic-162247263.html
A28: Oui | B28: OpenAI | C28: GPT-5 mini | D28: Petit | E28: Dense | G28: 25 | H28: 70 | K28: https://platform.openai.com/docs/models' | L28: USA | M28: 1.2 | N28: "Average for US data centers in 2023 (1.18, 1.35, 1.16, 1.28, 1.14, 1.15, 1.11) https://datacenters.microsoft.com/sustainability/efficiency/" | O28: 0.569 | P28: "Average for US data centers in 2023 (1.63, 0.74, 0.14, 0.25, 0.14, 0.95, 0.13) https://datacenters.microsoft.com/sustainability/efficiency/" | Q28: =IF( NOT(ISBLANK(F28)), F28, IF( AND(NOT(ISBLANK(G28)), NOT(ISBLANK(H28))), INT(AVERAGE(G28, H28)), "" ) ) -> 47 | R28: =IF( NOT(ISBLANK(I28)), INT(AVERAGE(I28,J28)), IF( AND(NOT(ISBLANK(G28)), NOT(ISBLANK(H28))), INT(AVERAGE(G28, H28)), "" ) ) -> 47 | S28: 64.1 | T28: 8.3 | U28: =0.062*(Tableau1[[#This Row],[Average TTFT]]/0.44) -> 1.1695455 | V28: 2000000000 | W28: https://www.feedough.com/openai-statistics/ https://www.demandsage.com/chatgpt-statistics/ | X28: =2.25*(10^12) -> 2250000000000 | Y28: =1500*(1-EXP(-(Tableau1[[#This Row],[P_total]]^2)/1000))*Tableau1[[#This Row],[P_total]]*10^9 -> 6.2758367e+13 | Z28: 45876 | AA28: Epoch Ai | AB28: =IF(Tableau1[[#This Row],[Date de publication]]>=EDATE(TODAY(),-24),"Oui","Non") -> Oui | AC28: 2000000 | AD28: https://finance.yahoo.com/sectors/technology/articles/coreweave-signs-multi-deal-anthropic-162247263.html
A29: Oui | B29: OpenAI | C29: GPT-5 nano | D29: Petit | E29: Dense | G29: 5 | H29: 18.5 | K29: https://platform.openai.com/docs/models' | L29: USA | M29: 1.2 | N29: "Average for US data centers in 2023 (1.18, 1.35, 1.16, 1.28, 1.14, 1.15, 1.11) https://datacenters.microsoft.com/sustainability/efficiency/" | O29: 0.569 | P29: "Average for US data centers in 2023 (1.63, 0.74, 0.14, 0.25, 0.14, 0.95, 0.13) https://datacenters.microsoft.com/sustainability/efficiency/" | Q29: =IF( NOT(ISBLANK(F29)), F29, IF( AND(NOT(ISBLANK(G29)), NOT(ISBLANK(H29))), INT(AVERAGE(G29, H29)), "" ) ) -> 11 | R29: =IF( NOT(ISBLANK(I29)), INT(AVERAGE(I29,J29)), IF( AND(NOT(ISBLANK(G29)), NOT(ISBLANK(H29))), INT(AVERAGE(G29, H29)), "" ) ) -> 11 | S29: 92.8 | T29: 6.94 | U29: =0.062*(Tableau1[[#This Row],[Average TTFT]]/0.44) -> 0.97790909 | V29: 2000000000 | W29: https://www.feedough.com/openai-statistics/ https://www.demandsage.com/chatgpt-statistics/ | X29: =2.25*(10^12) -> 2250000000000 | Y29: =1500*(1-EXP(-(Tableau1[[#This Row],[P_total]]^2)/1000))*Tableau1[[#This Row],[P_total]]*10^9 -> 1.8804397e+12 | Z29: 45876 | AA29: Epoch Ai | AB29: =IF(Tableau1[[#This Row],[Date de publication]]>=EDATE(TODAY(),-24),"Oui","Non") -> Oui | AC29: 2000000 | AD29: https://finance.yahoo.com/sectors/technology/articles/coreweave-signs-multi-deal-anthropic-162247263.html
A30: Oui | B30: OpenAI | C30: GPT-5.1 | D30: Grand | E30: MoE | F30: 300 | I30: 30 | J30: 90 | K30: https://platform.openai.com/docs/models' | L30: USA | M30: 1.2 | N30: "Average for US data centers in 2023 (1.18, 1.35, 1.16, 1.28, 1.14, 1.15, 1.11) https://datacenters.microsoft.com/sustainability/efficiency/" | O30: 0.569 | P30: "Average for US data centers in 2023 (1.63, 0.74, 0.14, 0.25, 0.14, 0.95, 0.13) https://datacenters.microsoft.com/sustainability/efficiency/" | Q30: =IF( NOT(ISBLANK(F30)), F30, IF( AND(NOT(ISBLANK(G30)), NOT(ISBLANK(H30))), INT(AVERAGE(G30, H30)), "" ) ) -> 300 | R30: =IF( NOT(ISBLANK(I30)), INT(AVERAGE(I30,J30)), IF( AND(NOT(ISBLANK(G30)), NOT(ISBLANK(H30))), INT(AVERAGE(G30, H30)), "" ) ) -> 60 | S30: 42.6 | T30: 1.11 | U30: =0.062*(Tableau1[[#This Row],[Average TTFT]]/0.44) -> 0.15640909 | V30: 2000000000 | W30: https://www.feedough.com/openai-statistics/ https://www.demandsage.com/chatgpt-statistics/ | X30: =2.25*(10^12) -> 2250000000000 | Y30: =1500*(1-EXP(-(Tableau1[[#This Row],[P_total]]^2)/1000))*Tableau1[[#This Row],[P_total]]*10^9 -> 450000000000000 | Z30: 45974 | AA30: Epoch Ai | AB30: =IF(Tableau1[[#This Row],[Date de publication]]>=EDATE(TODAY(),-24),"Oui","Non") -> Oui | AC30: 2000000 | AD30: https://finance.yahoo.com/sectors/technology/articles/coreweave-signs-multi-deal-anthropic-162247263.html
A31: Non | B31: OpenAI | C31: GPT-5.2 | D31: Grand | E31: MoE | F31: 420 | I31: 42 | J31: 126 | K31: https://platform.openai.com/docs/models' | L31: USA | M31: 1.2 | N31: "Average for US data centers in 2023 (1.18, 1.35, 1.16, 1.28, 1.14, 1.15, 1.11) https://datacenters.microsoft.com/sustainability/efficiency/" | O31: 0.569 | P31: "Average for US data centers in 2023 (1.63, 0.74, 0.14, 0.25, 0.14, 0.95, 0.13) https://datacenters.microsoft.com/sustainability/efficiency/" | Q31: =IF( NOT(ISBLANK(F31)), F31, IF( AND(NOT(ISBLANK(G31)), NOT(ISBLANK(H31))), INT(AVERAGE(G31, H31)), "" ) ) -> 420 | R31: =IF( NOT(ISBLANK(I31)), INT(AVERAGE(I31,J31)), IF( AND(NOT(ISBLANK(G31)), NOT(ISBLANK(H31))), INT(AVERAGE(G31, H31)), "" ) ) -> 84 | S31: 42.5 | T31: 3.47 | U31: =0.062*(Tableau1[[#This Row],[Average TTFT]]/0.44) -> 0.48895455 | V31: 2000000000 | W31: https://www.feedough.com/openai-statistics/ https://www.demandsage.com/chatgpt-statistics/ | X31: =2.25*(10^12) -> 2250000000000 | Y31: =1500*(1-EXP(-(Tableau1[[#This Row],[P_total]]^2)/1000))*Tableau1[[#This Row],[P_total]]*10^9 -> 630000000000000 | Z31: 46000 | AA31: Open Ai | AB31: =IF(Tableau1[[#This Row],[Date de publication]]>=EDATE(TODAY(),-24),"Oui","Non") -> Oui | AC31: 2000000 | AD31: https://finance.yahoo.com/sectors/technology/articles/coreweave-signs-multi-deal-anthropic-162247263.html
A32: Non | B32: OpenAI | C32: GPT-5.2 pro | D32: Grand | E32: MoE | F32: 5040 | I32: 504 | J32: 1512 | K32: https://platform.openai.com/docs/models' | L32: USA | M32: 1.2 | N32: "Average for US data centers in 2023 (1.18, 1.35, 1.16, 1.28, 1.14, 1.15, 1.11) https://datacenters.microsoft.com/sustainability/efficiency/" | O32: 0.569 | P32: "Average for US data centers in 2023 (1.63, 0.74, 0.14, 0.25, 0.14, 0.95, 0.13) https://datacenters.microsoft.com/sustainability/efficiency/" | Q32: =IF( NOT(ISBLANK(F32)), F32, IF( AND(NOT(ISBLANK(G32)), NOT(ISBLANK(H32))), INT(AVERAGE(G32, H32)), "" ) ) -> 5040 | R32: =IF( NOT(ISBLANK(I32)), INT(AVERAGE(I32,J32)), IF( AND(NOT(ISBLANK(G32)), NOT(ISBLANK(H32))), INT(AVERAGE(G32, H32)), "" ) ) -> 1008 | S32: 11.6 | T32: 32.5 | U32: =0.062*(Tableau1[[#This Row],[Average TTFT]]/0.44) -> 4.5795455 | V32: 2000000000 | W32: https://www.feedough.com/openai-statistics/ https://www.demandsage.com/chatgpt-statistics/ | X32: =2.25*(10^12) -> 2250000000000 | Y32: =1500*(1-EXP(-(Tableau1[[#This Row],[P_total]]^2)/1000))*Tableau1[[#This Row],[P_total]]*10^9 -> 7.56e+15 | Z32: 46000 | AA32: Open Ai | AB32: =IF(Tableau1[[#This Row],[Date de publication]]>=EDATE(TODAY(),-24),"Oui","Non") -> Oui | AC32: 2000000 | AD32: https://finance.yahoo.com/sectors/technology/articles/coreweave-signs-multi-deal-anthropic-162247263.html
A33: Non | B33: OpenAI | C33: o3 mini | D33: Petit | E33: Dense | G33: 8 | H33: 28 | K33: ['https://platform.openai.com/docs/models#o3-mini'] | L33: USA | M33: 1.2 | N33: "Average for US data centers in 2023 (1.18, 1.35, 1.16, 1.28, 1.14, 1.15, 1.11) https://datacenters.microsoft.com/sustainability/efficiency/" | O33: 0.569 | P33: "Average for US data centers in 2023 (1.63, 0.74, 0.14, 0.25, 0.14, 0.95, 0.13) https://datacenters.microsoft.com/sustainability/efficiency/" | Q33: =IF( NOT(ISBLANK(F33)), F33, IF( AND(NOT(ISBLANK(G33)), NOT(ISBLANK(H33))), INT(AVERAGE(G33, H33)), "" ) ) -> 18 | R33: =IF( NOT(ISBLANK(I33)), INT(AVERAGE(I33,J33)), IF( AND(NOT(ISBLANK(G33)), NOT(ISBLANK(H33))), INT(AVERAGE(G33, H33)), "" ) ) -> 18 | S33: 224.4 | T33: 6.7 | U33: =0.062*(Tableau1[[#This Row],[Average TTFT]]/0.44) -> 0.94409091 | V33: 2000000000 | W33: https://www.feedough.com/openai-statistics/ https://www.demandsage.com/chatgpt-statistics/ | X33: =2.25*(10^12) -> 2250000000000 | Y33: =1500*(1-EXP(-(Tableau1[[#This Row],[P_total]]^2)/1000))*Tableau1[[#This Row],[P_total]]*10^9 -> 7.4722435e+12 | Z33: 45688 | AA33: Epoch Ai | AB33: =IF(Tableau1[[#This Row],[Date de publication]]>=EDATE(TODAY(),-24),"Oui","Non") -> Oui | AC33: 2000000 | AD33: https://finance.yahoo.com/sectors/technology/articles/coreweave-signs-multi-deal-anthropic-162247263.html
A34: Oui | B34: OpenAI | C34: o4 mini | D34: Petit | E34: Dense | G34: 8 | H34: 28 | K34: ['https://platform.openai.com/docs/models#o3-mini'] | L34: USA | M34: 1.2 | N34: "Average for US data centers in 2023 (1.18, 1.35, 1.16, 1.28, 1.14, 1.15, 1.11) https://datacenters.microsoft.com/sustainability/efficiency/" | O34: 0.569 | P34: "Average for US data centers in 2023 (1.63, 0.74, 0.14, 0.25, 0.14, 0.95, 0.13) https://datacenters.microsoft.com/sustainability/efficiency/" | Q34: =IF( NOT(ISBLANK(F34)), F34, IF( AND(NOT(ISBLANK(G34)), NOT(ISBLANK(H34))), INT(AVERAGE(G34, H34)), "" ) ) -> 18 | R34: =IF( NOT(ISBLANK(I34)), INT(AVERAGE(I34,J34)), IF( AND(NOT(ISBLANK(G34)), NOT(ISBLANK(H34))), INT(AVERAGE(G34, H34)), "" ) ) -> 18 | S34: 98.6 | T34: 6.38 | U34: =0.062*(Tableau1[[#This Row],[Average TTFT]]/0.44) -> 0.899 | V34: 2000000000 | W34: https://www.feedough.com/openai-statistics/ https://www.demandsage.com/chatgpt-statistics/ | X34: =2.25*(10^12) -> 2250000000000 | Y34: =1500*(1-EXP(-(Tableau1[[#This Row],[P_total]]^2)/1000))*Tableau1[[#This Row],[P_total]]*10^9 -> 7.4722435e+12 | Z34: 45763 | AA34: Open Ai | AB34: =IF(Tableau1[[#This Row],[Date de publication]]>=EDATE(TODAY(),-24),"Oui","Non") -> Oui | AC34: 2000000 | AD34: https://finance.yahoo.com/sectors/technology/articles/coreweave-signs-multi-deal-anthropic-162247263.html
A35: Oui | B35: OpenAI | C35: text-embedding-3-large | D35: Embedding | F35: 8 | O35: 0.569 | Q35: =IF( NOT(ISBLANK(F35)), F35, IF( AND(NOT(ISBLANK(G35)), NOT(ISBLANK(H35))), INT(AVERAGE(G35, H35)), "" ) ) -> 8 | R35: =IF( NOT(ISBLANK(I35)), INT(AVERAGE(I35,J35)), IF( AND(NOT(ISBLANK(G35)), NOT(ISBLANK(H35))), INT(AVERAGE(G35, H35)), "" ) ) | U35: =0.062*(Tableau1[[#This Row],[Average TTFT]]/0.44) -> 0 | X35: =2.25*(10^12) -> 2250000000000 | Y35: =1500*(1-EXP(-(Tableau1[[#This Row],[P_total]]^2)/1000))*Tableau1[[#This Row],[P_total]]*10^9 -> 7.4394001e+11 | Z35: 43831 | AB35: =IF(Tableau1[[#This Row],[Date de publication]]>=EDATE(TODAY(),-24),"Oui","Non") -> Non
A36: Oui | B36: OpenAI | C36: GPT-5.6 Sol | D36: Grand | E36: MoE | F36: 900 | I36: 195 | K36: https://platform.openai.com/docs/models' | L36: USA | M36: 1.2 | N36: "Average for US data centers in 2023 (1.18, 1.35, 1.16, 1.28, 1.14, 1.15, 1.11) https://datacenters.microsoft.com/sustainability/efficiency/" | O36: 0.569 | P36: "Average for US data centers in 2023 (1.63, 0.74, 0.14, 0.25, 0.14, 0.95, 0.13) https://datacenters.microsoft.com/sustainability/efficiency/" | Q36: =IF( NOT(ISBLANK(F36)), F36, IF( AND(NOT(ISBLANK(G36)), NOT(ISBLANK(H36))), INT(AVERAGE(G36, H36)), "" ) ) -> 900 | R36: =IF( NOT(ISBLANK(I36)), INT(AVERAGE(I36,J36)), IF( AND(NOT(ISBLANK(G36)), NOT(ISBLANK(H36))), INT(AVERAGE(G36, H36)), "" ) ) -> 195 | S36: =(59+45+58)/3 -> 54 | T36: =(2.66+5.2+3.82)/3 -> 3.8933333 | U36: =0.062*(Tableau1[[#This Row],[Average TTFT]]/0.44) -> 0.54860606 | V36: 2000000000 | W36: https://www.feedough.com/openai-statistics/ https://www.demandsage.com/chatgpt-statistics/ | X36: =2.25*(10^12) -> 2250000000000 | Y36: =1500*(1-EXP(-(Tableau1[[#This Row],[P_total]]^2)/1000))*Tableau1[[#This Row],[P_total]]*10^9 -> 1.35e+15 | Z36: 46212 | AA36: Open AI | AB36: =IF(Tableau1[[#This Row],[Date de publication]]>=EDATE(TODAY(),-24),"Oui","Non") -> Oui | AC36: 2000000 | AD36: https://finance.yahoo.com/sectors/technology/articles/coreweave-signs-multi-deal-anthropic-162247263.html
A37: Oui | B37: OpenAI | C37: GPT-5.6 Terra | D37: Moyen | E37: Dense | G37: 25 | H37: 70 | K37: https://platform.openai.com/docs/models' | L37: USA | M37: 1.2 | N37: "Average for US data centers in 2023 (1.18, 1.35, 1.16, 1.28, 1.14, 1.15, 1.11) https://datacenters.microsoft.com/sustainability/efficiency/" | O37: 0.569 | P37: "Average for US data centers in 2023 (1.63, 0.74, 0.14, 0.25, 0.14, 0.95, 0.13) https://datacenters.microsoft.com/sustainability/efficiency/" | Q37: =IF( NOT(ISBLANK(F37)), F37, IF( AND(NOT(ISBLANK(G37)), NOT(ISBLANK(H37))), INT(AVERAGE(G37, H37)), "" ) ) -> 47 | R37: =IF( NOT(ISBLANK(I37)), INT(AVERAGE(I37,J37)), IF( AND(NOT(ISBLANK(G37)), NOT(ISBLANK(H37))), INT(AVERAGE(G37, H37)), "" ) ) -> 47 | S37: =(36+37+9)/3 -> 27.333333 | T37: =(4.86+0.5+3.9)/3 -> 3.0866667 | U37: =0.062*(Tableau1[[#This Row],[Average TTFT]]/0.44) -> 0.43493939 | V37: 2000000000 | W37: https://www.feedough.com/openai-statistics/ https://www.demandsage.com/chatgpt-statistics/ | X37: =2.25*(10^12) -> 2250000000000 | Y37: =1500*(1-EXP(-(Tableau1[[#This Row],[P_total]]^2)/1000))*Tableau1[[#This Row],[P_total]]*10^9 -> 6.2758367e+13 | Z37: 46212 | AA37: Open AI | AB37: =IF(Tableau1[[#This Row],[Date de publication]]>=EDATE(TODAY(),-24),"Oui","Non") -> Oui | AC37: 2000000 | AD37: https://finance.yahoo.com/sectors/technology/articles/coreweave-signs-multi-deal-anthropic-162247263.html
A38: Oui | B38: OpenAI | C38: GPT-5.6 Luna | D38: Petit | E38: Dense | G38: 5 | H38: 18.5 | K38: https://platform.openai.com/docs/models' | L38: USA | M38: 1.2 | N38: "Average for US data centers in 2023 (1.18, 1.35, 1.16, 1.28, 1.14, 1.15, 1.11) https://datacenters.microsoft.com/sustainability/efficiency/" | O38: 0.569 | P38: "Average for US data centers in 2023 (1.63, 0.74, 0.14, 0.25, 0.14, 0.95, 0.13) https://datacenters.microsoft.com/sustainability/efficiency/" | Q38: =IF( NOT(ISBLANK(F38)), F38, IF( AND(NOT(ISBLANK(G38)), NOT(ISBLANK(H38))), INT(AVERAGE(G38, H38)), "" ) ) -> 11 | R38: =IF( NOT(ISBLANK(I38)), INT(AVERAGE(I38,J38)), IF( AND(NOT(ISBLANK(G38)), NOT(ISBLANK(H38))), INT(AVERAGE(G38, H38)), "" ) ) -> 11 | S38: =(58+58+3)/3 -> 39.666667 | T38: =(4.39+2.83+8.78)/3 -> 5.3333333 | U38: =0.062*(Tableau1[[#This Row],[Average TTFT]]/0.44) -> 0.75151515 | V38: 2000000000 | W38: https://www.feedough.com/openai-statistics/ https://www.demandsage.com/chatgpt-statistics/ | X38: =2.25*(10^12) -> 2250000000000 | Y38: =1500*(1-EXP(-(Tableau1[[#This Row],[P_total]]^2)/1000))*Tableau1[[#This Row],[P_total]]*10^9 -> 1.8804397e+12 | Z38: 46212 | AA38: Open AI | AB38: =IF(Tableau1[[#This Row],[Date de publication]]>=EDATE(TODAY(),-24),"Oui","Non") -> Oui | AC38: 2000000 | AD38: https://finance.yahoo.com/sectors/technology/articles/coreweave-signs-multi-deal-anthropic-162247263.html
A39: Oui | B39: Anthropic | C39: Claude Sonnet 5 | D39: Grand | E39: MoE | F39: 440 | I39: 44 | J39: 132 | K39: ['https://docs.anthropic.com/en/docs/about-claude/models'] | L39: USA | M39: =AVERAGE(1.09,1.14) -> 1.115 | N39: "- 1.09 for Google in 2024, average of US data centers (https://www.gstatic.com/gumdrop/sustainability/google-2025-environmental-report.pdf) - 1.14 for AWS in 2024 (https://sustainability.aboutamazon.com/products-services/aws-cloud)" | O39: =AVERAGE(0.13,0.99) -> 0.56 | P39: "- 0.13 for AWS in 2024 (https://sustainability.aboutamazon.com/products-services/aws-cloud) - 0.999 for Google in 2024 (https://www.gstatic.com/gumdrop/sustainability/google-2025-environmental-report.pdf)" | Q39: =IF( NOT(ISBLANK(F39)), F39, IF( AND(NOT(ISBLANK(G39)), NOT(ISBLANK(H39))), INT(AVERAGE(G39, H39)), "" ) ) -> 440 | R39: =IF( NOT(ISBLANK(I39)), INT(AVERAGE(I39,J39)), IF( AND(NOT(ISBLANK(G39)), NOT(ISBLANK(H39))), INT(AVERAGE(G39, H39)), "" ) ) -> 88 | S39: =(49+45+59+75)/4 -> 57 | T39: =(2.57+2.61+3.57+2.8)/4 -> 2.8875 | U39: =0.062*(Tableau1[[#This Row],[Average TTFT]]/0.44) -> 0.406875 | V39: 1000000000 | W39: https://www.demandsage.com/claude-ai-statistics/ | X39: =2.25*(10^12) -> 2250000000000 | Y39: =1500*(1-EXP(-(Tableau1[[#This Row],[P_total]]^2)/1000))*Tableau1[[#This Row],[P_total]]*10^9 -> 660000000000000 | Z39: 46203 | AA39: Antrhopic | AB39: =IF(Tableau1[[#This Row],[Date de publication]]>=EDATE(TODAY(),-24),"Oui","Non") -> Oui | AC39: 1400000 | AD39: https://wccftech.com/openai-sets-goal-to-scale-up-ai-compute-capacity-to-a-whopping-30gw-by-2030/
A40: Oui | B40: Anthropic | C40: Claude Opus 4.8 | D40: Grand | E40: MoE | F40: 670 | I40: 66.5 | J40: 199.5 | K40: ['https://calculator.ecologits.ai/'] | L40: USA | M40: =AVERAGE(1.09,1.14) -> 1.115 | N40: "- 1.09 for Google in 2024, average of US data centers (https://www.gstatic.com/gumdrop/sustainability/google-2025-environmental-report.pdf) - 1.14 for AWS in 2024 (https://sustainability.aboutamazon.com/products-services/aws-cloud)" | O40: =AVERAGE(0.13,0.99) -> 0.56 | P40: "- 0.13 for AWS in 2024 (https://sustainability.aboutamazon.com/products-services/aws-cloud) - 0.999 for Google in 2024 (https://www.gstatic.com/gumdrop/sustainability/google-2025-environmental-report.pdf)" | Q40: =IF( NOT(ISBLANK(F40)), F40, IF( AND(NOT(ISBLANK(G40)), NOT(ISBLANK(H40))), INT(AVERAGE(G40, H40)), "" ) ) -> 670 | R40: =IF( NOT(ISBLANK(I40)), INT(AVERAGE(I40,J40)), IF( AND(NOT(ISBLANK(G40)), NOT(ISBLANK(H40))), INT(AVERAGE(G40, H40)), "" ) ) -> 133 | S40: 58 | T40: 1.63 | U40: =0.062*(Tableau1[[#This Row],[Average TTFT]]/0.44) -> 0.22968182 | V40: 1000000000 | W40: https://www.demandsage.com/claude-ai-statistics/ | X40: =2.25*(10^12) -> 2250000000000 | Y40: =1500*(1-EXP(-(Tableau1[[#This Row],[P_total]]^2)/1000))*Tableau1[[#This Row],[P_total]]*10^9 -> 1.005e+15 | Z40: 46170 | AA40: Antrhopic | AB40: =IF(Tableau1[[#This Row],[Date de publication]]>=EDATE(TODAY(),-24),"Oui","Non") -> Oui | AC40: 1400000 | AD40: https://wccftech.com/openai-sets-goal-to-scale-up-ai-compute-capacity-to-a-whopping-30gw-by-2030/
A41: Oui | B41: Google | C41: Gemini 3.5 flash | D41: Grand | E41: MoE | F41: 900 | I41: 83 | J41: 248 | K41: ['https://calculator.ecologits.ai/'] | L41: USA | M41: 1.2 | N41: Average for US data centers in 2024 (1.06, 1.11, 1.07, 1.10, 1.06, 1.09, 1.09, 1.10, 1.13, 1.09, 1.08, 1.11, 1.10, 1.10, 1.07, 1.09, 1.16)_x000D_ https://www.gstatic.com/gumdrop/sustainability/google-2025-environmental-report.pdf (page 109) | O41: 0.99 | P41: "Total data center electricity consumption and water consumption in 2024 are respectively 30,825,600 MWh and 8,135 Million gallons. https://www.gstatic.com/gumdrop/sustainability/google-2025-environmental-report.pdf" | Q41: =IF( NOT(ISBLANK(F41)), F41, IF( AND(NOT(ISBLANK(G41)), NOT(ISBLANK(H41))), INT(AVERAGE(G41, H41)), "" ) ) -> 900 | R41: =IF( NOT(ISBLANK(I41)), INT(AVERAGE(I41,J41)), IF( AND(NOT(ISBLANK(G41)), NOT(ISBLANK(H41))), INT(AVERAGE(G41, H41)), "" ) ) -> 165 | S41: 130.6 | T41: 2.72 | U41: =0.062*(Tableau1[[#This Row],[Average TTFT]]/0.44) -> 0.38327273 | V41: 3000000000 | W41: https://www.technobezz.com/news/google-slashes-free-gemini-api-requests-to-20-per-day-2025-12-20-gl06 | X41: =2.25*(10^12) -> 2250000000000 | Y41: =1500*(1-EXP(-(Tableau1[[#This Row],[P_total]]^2)/1000))*Tableau1[[#This Row],[P_total]]*10^9 -> 1.35e+15 | Z41: 46161 | AA41: Numerama | AB41: =IF(Tableau1[[#This Row],[Date de publication]]>=EDATE(TODAY(),-24),"Oui","Non") -> Oui | AC41: 9000000 | AD41: https://www.cnbc.com/2025/11/21/google-must-double-ai-serving-capacity-every-6-months-to-meet-demand.html
F120: =IF(gpu_nb<=1,1, IF(gpu_nb<=2,2, IF(gpu_nb<=4,4, IF(gpu_nb<=8,8, IF(gpu_nb<=16,16, IF(gpu_nb<=32,32, IF(gpu_nb<=64,64,"ERREUR") ) ) ) ) ) ) -> #NAME?
F121: =1.2*model_total_parameter_count*(MODEL_QUANTIZATION_BITS/8) -> #NAME?
F122: =ROUNDUP(model_required_memory/GPU_MEMORY,1) -> #NAME?
F126: =gpu_energy*gpu_required_count -> #NAME?
F127: =(output_token_count*gpu_energy_per_token)/1000 -> #NAME? | G127: kWh
F128: =((GPU_ENERGY_ALPHA*EXP(GPU_ENERGY_BETA*BATCH_SIZE)*model_active_parameter_count+GPU_ENERGY_GAMMA)) -> #NAME? | G128: Wh/token
F134: =MIN(request_latency,gpu_latency_t_prefill) -> #NAME?
E135: Latence du génération selon Ecologits | F135: =MIN(F142) -> #NAME? | G135: sec
E142: Latence du GPU | F142: =output_token_count*latency_per_token+latency_first_token -> #NAME? | G142: sec
F146: =(generation_latency / 3600) * SERVER_POWER * (gpu_required_count / server_gpu_count) * (1 / BATCH_SIZE) -> #NAME?
E147: Electricité consommée par le serveur selon Ecologits | F147: =(F135/3600) *SERVER_POWER *(gpu_required_count/server_gpu_count) *(1/BATCH_SIZE) -> #NAME? | G147: kWh
F159: =datacenter_pue*(F147+(gpu_energy*gpu_required_count)) -> #NAME?
F163: =(request_energy *(datacenter_wue +datacenter_pue*electricity_mix_wue) ) -> #NAME? | G163: L
F164: =(request_global_energy *(datacenter_wue +datacenter_pue*electricity_mix_wue) )+F168+F173 -> #NAME?
F182: =request_energy*electricity_mix_gwp_FR -> #NAME?
E192: GES embarqué du projet [request_global_embodied_gwp]
F193: =(F135*F198)/(HARDWARE_LIFESPAN*BATCH_SIZE) -> #NAME?
F194: =(gpu_total_elec+server_energy+network_energy)*bati_electricity_mix_gwp -> #NAME?
F197: =generation_latency *(gpu_required_count/server_gpu_count)*server_embodied_gwp +(gpu_required_count*gpu_embodied_gwp) /(BATCH_SIZE*serveur_lifespan) -> #NAME?
E198: GES embarqué d'un serveur selon Ecologits | F198: =generation_latency *(gpu_required_count/server_gpu_count)*5700 +(gpu_required_count*gpu_embodied_gwp) /(BATCH_SIZE*serveur_lifespan) -> #NAME?

Sheet Paramètres
B1: Libellé | C1: Tokens | E1: Fournisseurs | F1: Modèle | G1: Catégorie | H1: =E2 -> Anthropic | I1: =E3 -> Google | J1: =E4 -> Mistral AI | K1: =E5 -> OpenAI | M1: {=_xlfn.UNIQUE(Tableau1[Fournisseurs])} -> Anthropic | N1: Catégorie | O1: {=_xlfn._xlws.FILTER( Tableau1[Nom du modèle], (Tableau1[Fournisseurs]='⚙️Données'!$F$26)*(Tableau1[Catégorie]<>"Embedding"))} -> #VALUE! | Q1: {=TRANSPOSE(_xlfn.UNIQUE(Tableau1[Fournisseurs]))} -> Anthropic | R1: Google | S1: Mistral AI | T1: OpenAI | V1: Modèle 1 | W1: Modèle 2 | X1: Modèle 3 | Y1: Modèle 4 | Z1: Modèle 5 | AB1: Pays pour FE electricité
B2: Echange court (≈ 400 tokens) | C2: 400 | E2: {=_xlfn.UNIQUE(Tableau1[Fournisseurs])} -> Anthropic | F2: {=_xlfn._xlws.FILTER(Tableau1[Nom du modèle],Tableau1[Fournisseurs]='⚙️Données'!F26)} -> #VALUE! | G2: =_xlfn.XLOOKUP('⚙️Données'!J26,Tableau1[Nom du modèle],Tableau1[Catégorie]) -> #N/A | H2: {=_xlfn._xlws.FILTER( Tableau1[Nom du modèle], (Tableau1[Fournisseurs]=H1)* (Tableau1[Catégorie]=$G$2),"Aucun modèle disponible" )} -> #N/A | I2: {=_xlfn._xlws.FILTER( Tableau1[Nom du modèle], (Tableau1[Fournisseurs]=I1)* (Tableau1[Catégorie]=$G$2) )} -> #N/A | J2: {=_xlfn._xlws.FILTER( Tableau1[Nom du modèle], (Tableau1[Fournisseurs]=J1)* (Tableau1[Catégorie]=$G$2) )} -> #N/A | K2: {=_xlfn._xlws.FILTER( Tableau1[Nom du modèle], (Tableau1[Fournisseurs]=K1)* (Tableau1[Catégorie]=$G$2) )} -> #N/A | M2: Google | N2: {=_xlfn.UNIQUE(Tableau1[Catégorie])} -> Moyen | Q2: {=_xlfn._xlws.FILTER( Tableau1[Nom du modèle], (Tableau1[Fournisseurs]=Q1)*(Tableau1[Catégorie]<>"Embedding"))} -> Claude Haiku 3 | R2: {=_xlfn._xlws.FILTER( Tableau1[Nom du modèle], (Tableau1[Fournisseurs]=R1)*(Tableau1[Catégorie]<>"Embedding"))} -> Gemini 2.5 flash | S2: {=_xlfn._xlws.FILTER( Tableau1[Nom du modèle], (Tableau1[Fournisseurs]=S1)*(Tableau1[Catégorie]<>"Embedding"))} -> Codestral | T2: {=_xlfn._xlws.FILTER( Tableau1[Nom du modèle], (Tableau1[Fournisseurs]=T1)*(Tableau1[Catégorie]<>"Embedding"))} -> GPT-4 | V2: {=_xlfn._xlws.FILTER( Tableau1[Nom du modèle], (Tableau1[Fournisseurs]=#REF!)*(Tableau1[Catégorie]<>"Embedding"))} -> #REF! | W2: {=_xlfn._xlws.FILTER( Tableau1[Nom du modèle], (Tableau1[Fournisseurs]=#REF!)*(Tableau1[Catégorie]<>"Embedding"))} -> #REF! | X2: {=_xlfn._xlws.FILTER( Tableau1[Nom du modèle], (Tableau1[Fournisseurs]=#REF!)*(Tableau1[Catégorie]<>"Embedding"))} -> #REF! | Y2: {=_xlfn._xlws.FILTER( Tableau1[Nom du modèle], (Tableau1[Fournisseurs]=#REF!)*(Tableau1[Catégorie]<>"Embedding"))} -> #REF! | Z2: {=_xlfn._xlws.FILTER( Tableau1[Nom du modèle], (Tableau1[Fournisseurs]=#REF!)*(Tableau1[Catégorie]<>"Embedding"))} -> #REF! | AB2: {=(_xlfn._xlws.FILTER(Tableau2[Sous-catégorie],Tableau2[Catégorie]="electricité","null"))} -> France
B3: Réponse détaillée (≈ 1000 tokens) | C3: 1000 | E3: Google | M3: Mistral AI | N3: Grand | Q3: Claude Haiku 4.5 | R3: Gemini 2.5 flash image | S3: Magistral Medium | T3: GPT-4 turbo | AB3: Autre (monde)
B4: Analyse longue (≈ 1500 tokens) | C4: 1500 | E4: Mistral AI | M4: OpenAI | N4: Hors catégorie | Q4: Claude Sonnet 3.7 | R4: Gemini 2.5 flash lite | S4: Ministral 3b | T4: GPT-4.1 | AB4: Europe (UE27)
E5: OpenAI | N5: Petit | Q5: Claude Sonnet 4 | R5: Gemini 2.5 pro | S5: Ministral 8b | T5: GPT-4.1 nano | AB5: USA
N6: Embedding | Q6: Claude Sonnet 4.5 | R6: Gemini 3.5 flash | S6: Mistral Large | T6: GPT-4.1-mini | AB6: UK
Q7: Claude Sonnet 4.6 | S7: Mistral Medium | T7: GPT-4o | AB7: Allemagne
Q8: Claude Opus 4.6 | S8: Pixtral Large | T8: GPT-4o mini | AB8: Irlande
Q9: Claude Sonnet 5 | T9: GPT-5 | AB9: Pays Bas
Q10: Claude Opus 4.8 | T10: GPT-5 mini | AB10: Suède
T11: GPT-5 nano
T12: GPT-5.1
T13: GPT-5.2
T14: GPT-5.2 pro
T15: o3 mini
T16: o4 mini
T17: GPT-5.6 Sol
T18: GPT-5.6 Terra
T19: GPT-5.6 Luna
